{
    "guid": "8c30f4a2-5dd5-430d-a348-7737b72980ed",
    "id": 1000010,
    "title": "Lucky Day_Infraction_100bpm.mp3",
    "createdAt": 1687944370,
    "updatedAt": 1687952264,
    "bpm": 100,
    "signature": 4,
    "fileName": "",
    "difficulty": 2,
    "noteList": [
        {
            "noteType": 0,
            "laneNum": 2,
            "startTime": 2.4,
            "endTime": 2.4
        },
        {
            "noteType": 1,
            "laneNum": 0,
            "startTime": 2.7,
            "endTime": 3.0
        },
        {
            "noteType": 1,
            "laneNum": 3,
            "startTime": 2.7,
            "endTime": 3.0
        },
        {
            "noteType": 0,
            "laneNum": 1,
            "startTime": 2.85,
            "endTime": 2.85
        },
        {
            "noteType": 0,
            "laneNum": 2,
            "startTime": 3.15,
            "endTime": 3.15
        },
        {
            "noteType": 1,
            "laneNum": 0,
            "startTime": 3.3,
            "endTime": 3.6
        },
        {
            "noteType": 0,
            "laneNum": 3,
            "startTime": 3.3,
            "endTime": 3.3
        },
        {
            "noteType": 0,
            "laneNum": 2,
            "startTime": 3.6,
            "endTime": 3.6
        },
        {
            "noteType": 1,
            "laneNum": 0,
            "startTime": 3.9,
            "endTime": 4.2
        },
        {
            "noteType": 0,
            "laneNum": 3,
            "startTime": 4.05,
            "endTime": 4.05
        },
        {
            "noteType": 0,
            "laneNum": 1,
            "startTime": 4.35,
            "endTime": 4.35
        },
        {
            "noteType": 0,
            "laneNum": 2,
            "startTime": 4.5,
            "endTime": 4.5
        },
        {
            "noteType": 1,
            "laneNum": 3,
            "startTime": 4.5,
            "endTime": 4.8
        },
        {
            "noteType": 0,
            "laneNum": 1,
            "startTime": 4.65,
            "endTime": 4.65
        },
        {
            "noteType": 0,
            "laneNum": 0,
            "startTime": 4.8,
            "endTime": 4.8
        },
        {
            "noteType": 1,
            "laneNum": 0,
            "startTime": 5.1,
            "endTime": 5.4
        },
        {
            "noteType": 1,
            "laneNum": 3,
            "startTime": 5.1,
            "endTime": 5.4
        },
        {
            "noteType": 0,
            "laneNum": 2,
            "startTime": 5.25,
            "endTime": 5.25
        },
        {
            "noteType": 0,
            "laneNum": 1,
            "startTime": 5.55,
            "endTime": 5.55
        },
        {
            "noteType": 1,
            "laneNum": 0,
            "startTime": 5.7,
            "endTime": 6.0
        },
        {
            "noteType": 0,
            "laneNum": 2,
            "startTime": 5.7,
            "endTime": 5.7
        },
        {
            "noteType": 0,
            "laneNum": 3,
            "startTime": 6.0,
            "endTime": 6.0
        },
        {
            "noteType": 1,
            "laneNum": 3,
            "startTime": 6.3,
            "endTime": 6.6
        },
        {
            "noteType": 0,
            "laneNum": 1,
            "startTime": 6.45,
            "endTime": 6.45
        },
        {
            "noteType": 0,
            "laneNum": 0,
            "startTime": 6.75,
            "endTime": 6.75
        },
        {
            "noteType": 0,
            "laneNum": 1,
            "startTime": 6.9,
            "endTime": 6.9
        },
        {
            "noteType": 1,
            "laneNum": 2,
            "startTime": 6.9,
            "endTime": 7.2
        },
        {
            "noteType": 0,
            "laneNum": 3,
            "startTime": 7.2,
            "endTime": 7.2
        },
        {
            "noteType": 1,
            "laneNum": 1,
            "startTime": 7.5,
            "endTime": 7.8
        },
        {
            "noteType": 1,
            "laneNum": 3,
            "startTime": 7.5,
            "endTime": 7.8
        },
        {
            "noteType": 0,
            "laneNum": 2,
            "startTime": 7.65,
            "endTime": 7.65
        },
        {
            "noteType": 0,
            "laneNum": 0,
            "startTime": 7.95,
            "endTime": 7.95
        },
        {
            "noteType": 0,
            "laneNum": 1,
            "startTime": 8.1,
            "endTime": 8.1
        },
        {
            "noteType": 1,
            "laneNum": 3,
            "startTime": 8.1,
            "endTime": 8.4
        },
        {
            "noteType": 0,
            "laneNum": 2,
            "startTime": 8.4,
            "endTime": 8.4
        },
        {
            "noteType": 1,
            "laneNum": 3,
            "startTime": 8.7,
            "endTime": 9.0
        },
        {
            "noteType": 0,
            "laneNum": 0,
            "startTime": 8.85,
            "endTime": 8.85
        },
        {
            "noteType": 0,
            "laneNum": 1,
            "startTime": 9.15,
            "endTime": 9.15
        },
        {
            "noteType": 0,
            "laneNum": 2,
            "startTime": 9.3,
            "endTime": 9.3
        },
        {
            "noteType": 1,
            "laneNum": 3,
            "startTime": 9.3,
            "endTime": 9.6
        },
        {
            "noteType": 0,
            "laneNum": 1,
            "startTime": 9.45,
            "endTime": 9.45
        },
        {
            "noteType": 0,
            "laneNum": 0,
            "startTime": 9.6,
            "endTime": 9.6
        },
        {
            "noteType": 1,
            "laneNum": 2,
            "startTime": 9.9,
            "endTime": 10.2
        },
        {
            "noteType": 1,
            "laneNum": 3,
            "startTime": 9.9,
            "endTime": 10.2
        },
        {
            "noteType": 0,
            "laneNum": 1,
            "startTime": 10.05,
            "endTime": 10.05
        },
        {
            "noteType": 0,
            "laneNum": 0,
            "startTime": 10.35,
            "endTime": 10.35
        },
        {
            "noteType": 1,
            "laneNum": 2,
            "startTime": 10.5,
            "endTime": 10.8
        },
        {
            "noteType": 0,
            "laneNum": 3,
            "startTime": 10.5,
            "endTime": 10.5
        },
        {
            "noteType": 0,
            "laneNum": 1,
            "startTime": 10.8,
            "endTime": 10.8
        },
        {
            "noteType": 1,
            "laneNum": 0,
            "startTime": 11.1,
            "endTime": 11.4
        },
        {
            "noteType": 0,
            "laneNum": 2,
            "startTime": 11.25,
            "endTime": 11.25
        },
        {
            "noteType": 0,
            "laneNum": 3,
            "startTime": 11.55,
            "endTime": 11.55
        },
        {
            "noteType": 0,
            "laneNum": 1,
            "startTime": 11.7,
            "endTime": 11.7
        },
        {
            "noteType": 1,
            "laneNum": 2,
            "startTime": 11.7,
            "endTime": 12.0
        },
        {
            "noteType": 0,
            "laneNum": 3,
            "startTime": 12.0,
            "endTime": 12.0
        },
        {
            "noteType": 1,
            "laneNum": 2,
            "startTime": 12.3,
            "endTime": 12.6
        },
        {
            "noteType": 1,
            "laneNum": 3,
            "startTime": 12.3,
            "endTime": 12.6
        },
        {
            "noteType": 0,
            "laneNum": 0,
            "startTime": 12.45,
            "endTime": 12.45
        },
        {
            "noteType": 0,
            "laneNum": 1,
            "startTime": 12.75,
            "endTime": 12.75
        },
        {
            "noteType": 0,
            "laneNum": 2,
            "startTime": 12.9,
            "endTime": 12.9
        },
        {
            "noteType": 1,
            "laneNum": 3,
            "startTime": 12.9,
            "endTime": 13.2
        },
        {
            "noteType": 0,
            "laneNum": 0,
            "startTime": 13.2,
            "endTime": 13.2
        },
        {
            "noteType": 1,
            "laneNum": 2,
            "startTime": 13.5,
            "endTime": 13.8
        },
        {
            "noteType": 0,
            "laneNum": 1,
            "startTime": 13.65,
            "endTime": 13.65
        },
        {
            "noteType": 0,
            "laneNum": 3,
            "startTime": 13.95,
            "endTime": 13.95
        },
        {
            "noteType": 0,
            "laneNum": 2,
            "startTime": 14.1,
            "endTime": 14.1
        },
        {
            "noteType": 1,
            "laneNum": 3,
            "startTime": 14.1,
            "endTime": 14.4
        },
        {
            "noteType": 0,
            "laneNum": 1,
            "startTime": 14.25,
            "endTime": 14.25
        },
        {
            "noteType": 0,
            "laneNum": 0,
            "startTime": 14.4,
            "endTime": 14.4
        },
        {
            "noteType": 1,
            "laneNum": 0,
            "startTime": 14.7,
            "endTime": 15.0
        },
        {
            "noteType": 1,
            "laneNum": 1,
            "startTime": 14.7,
            "endTime": 15.0
        },
        {
            "noteType": 0,
            "laneNum": 3,
            "startTime": 14.85,
            "endTime": 14.85
        },
        {
            "noteType": 0,
            "laneNum": 2,
            "startTime": 15.15,
            "endTime": 15.15
        },
        {
            "noteType": 0,
            "laneNum": 0,
            "startTime": 15.3,
            "endTime": 15.3
        },
        {
            "noteType": 1,
            "laneNum": 3,
            "startTime": 15.3,
            "endTime": 15.6
        },
        {
            "noteType": 0,
            "laneNum": 1,
            "startTime": 15.6,
            "endTime": 15.6
        },
        {
            "noteType": 1,
            "laneNum": 3,
            "startTime": 15.9,
            "endTime": 16.2
        },
        {
            "noteType": 0,
            "laneNum": 0,
            "startTime": 16.05,
            "endTime": 16.05
        },
        {
            "noteType": 0,
            "laneNum": 2,
            "startTime": 16.35,
            "endTime": 16.35
        },
        {
            "noteType": 1,
            "laneNum": 0,
            "startTime": 16.5,
            "endTime": 16.8
        },
        {
            "noteType": 0,
            "laneNum": 1,
            "startTime": 16.5,
            "endTime": 16.5
        },
        {
            "noteType": 0,
            "laneNum": 3,
            "startTime": 16.8,
            "endTime": 16.8
        },
        {
            "noteType": 1,
            "laneNum": 2,
            "startTime": 17.1,
            "endTime": 17.4
        },
        {
            "noteType": 1,
            "laneNum": 3,
            "startTime": 17.1,
            "endTime": 17.4
        },
        {
            "noteType": 0,
            "laneNum": 1,
            "startTime": 17.25,
            "endTime": 17.25
        },
        {
            "noteType": 0,
            "laneNum": 0,
            "startTime": 17.55,
            "endTime": 17.55
        },
        {
            "noteType": 0,
            "laneNum": 1,
            "startTime": 17.7,
            "endTime": 17.7
        },
        {
            "noteType": 1,
            "laneNum": 2,
            "startTime": 17.7,
            "endTime": 18.0
        },
        {
            "noteType": 0,
            "laneNum": 3,
            "startTime": 18.0,
            "endTime": 18.0
        },
        {
            "noteType": 1,
            "laneNum": 2,
            "startTime": 18.3,
            "endTime": 18.6
        },
        {
            "noteType": 0,
            "laneNum": 1,
            "startTime": 18.45,
            "endTime": 18.45
        },
        {
            "noteType": 0,
            "laneNum": 0,
            "startTime": 18.75,
            "endTime": 18.75
        },
        {
            "noteType": 1,
            "laneNum": 0,
            "startTime": 18.9,
            "endTime": 19.2
        },
        {
            "noteType": 0,
            "laneNum": 3,
            "startTime": 18.9,
            "endTime": 18.9
        },
        {
            "noteType": 0,
            "laneNum": 1,
            "startTime": 19.05,
            "endTime": 19.05
        },
        {
            "noteType": 0,
            "laneNum": 2,
            "startTime": 19.2,
            "endTime": 19.2
        },
        {
            "noteType": 1,
            "laneNum": 1,
            "startTime": 19.5,
            "endTime": 19.8
        },
        {
            "noteType": 1,
            "laneNum": 3,
            "startTime": 19.5,
            "endTime": 19.8
        },
        {
            "noteType": 0,
            "laneNum": 0,
            "startTime": 19.65,
            "endTime": 19.65
        },
        {
            "noteType": 0,
            "laneNum": 2,
            "startTime": 19.95,
            "endTime": 19.95
        },
        {
            "noteType": 1,
            "laneNum": 0,
            "startTime": 20.1,
            "endTime": 20.4
        },
        {
            "noteType": 0,
            "laneNum": 1,
            "startTime": 20.1,
            "endTime": 20.1
        },
        {
            "noteType": 0,
            "laneNum": 3,
            "startTime": 20.4,
            "endTime": 20.4
        },
        {
            "noteType": 1,
            "laneNum": 1,
            "startTime": 20.7,
            "endTime": 21.0
        },
        {
            "noteType": 0,
            "laneNum": 2,
            "startTime": 20.85,
            "endTime": 20.85
        },
        {
            "noteType": 1,
            "laneNum": 0,
            "startTime": 21.15,
            "endTime": 21.6
        },
        {
            "noteType": 0,
            "laneNum": 3,
            "startTime": 21.15,
            "endTime": 21.15
        },
        {
            "noteType": 0,
            "laneNum": 1,
            "startTime": 21.3,
            "endTime": 21.3
        },
        {
            "noteType": 1,
            "laneNum": 2,
            "startTime": 21.6,
            "endTime": 22.05
        },
        {
            "noteType": 1,
            "laneNum": 3,
            "startTime": 21.6,
            "endTime": 26.4
        },
        {
            "noteType": 0,
            "laneNum": 0,
            "startTime": 22.05,
            "endTime": 22.05
        },
        {
            "noteType": 0,
            "laneNum": 1,
            "startTime": 22.35,
            "endTime": 22.35
        },
        {
            "noteType": 0,
            "laneNum": 0,
            "startTime": 22.5,
            "endTime": 22.5
        },
        {
            "noteType": 0,
            "laneNum": 1,
            "startTime": 22.8,
            "endTime": 22.8
        },
        {
            "noteType": 1,
            "laneNum": 2,
            "startTime": 23.25,
            "endTime": 24.0
        },
        {
            "noteType": 0,
            "laneNum": 0,
            "startTime": 23.55,
            "endTime": 23.55
        },
        {
            "noteType": 0,
            "laneNum": 1,
            "startTime": 23.7,
            "endTime": 23.7
        },
        {
            "noteType": 0,
            "laneNum": 0,
            "startTime": 23.85,
            "endTime": 23.85
        },
        {
            "noteType": 0,
            "laneNum": 1,
            "startTime": 24.0,
            "endTime": 24.0
        },
        {
            "noteType": 0,
            "laneNum": 0,
            "startTime": 24.45,
            "endTime": 24.45
        },
        {
            "noteType": 0,
            "laneNum": 1,
            "startTime": 24.75,
            "endTime": 24.75
        },
        {
            "noteType": 0,
            "laneNum": 2,
            "startTime": 24.9,
            "endTime": 24.9
        },
        {
            "noteType": 1,
            "laneNum": 0,
            "startTime": 25.2,
            "endTime": 25.65
        },
        {
            "noteType": 1,
            "laneNum": 2,
            "startTime": 25.2,
            "endTime": 25.65
        },
        {
            "noteType": 0,
            "laneNum": 1,
            "startTime": 25.65,
            "endTime": 25.65
        },
        {
            "noteType": 0,
            "laneNum": 0,
            "startTime": 25.95,
            "endTime": 25.95
        },
        {
            "noteType": 0,
            "laneNum": 2,
            "startTime": 26.1,
            "endTime": 26.1
        },
        {
            "noteType": 1,
            "laneNum": 0,
            "startTime": 26.4,
            "endTime": 31.2
        },
        {
            "noteType": 1,
            "laneNum": 1,
            "startTime": 26.4,
            "endTime": 26.85
        },
        {
            "noteType": 0,
            "laneNum": 3,
            "startTime": 27.3,
            "endTime": 27.3
        },
        {
            "noteType": 0,
            "laneNum": 2,
            "startTime": 27.6,
            "endTime": 27.6
        },
        {
            "noteType": 1,
            "laneNum": 1,
            "startTime": 28.05,
            "endTime": 28.8
        },
        {
            "noteType": 0,
            "laneNum": 2,
            "startTime": 28.35,
            "endTime": 28.35
        },
        {
            "noteType": 0,
            "laneNum": 3,
            "startTime": 28.5,
            "endTime": 28.5
        },
        {
            "noteType": 0,
            "laneNum": 2,
            "startTime": 28.65,
            "endTime": 28.65
        },
        {
            "noteType": 0,
            "laneNum": 3,
            "startTime": 28.8,
            "endTime": 28.8
        },
        {
            "noteType": 0,
            "laneNum": 2,
            "startTime": 29.25,
            "endTime": 29.25
        },
        {
            "noteType": 0,
            "laneNum": 1,
            "startTime": 29.55,
            "endTime": 29.55
        },
        {
            "noteType": 0,
            "laneNum": 2,
            "startTime": 29.7,
            "endTime": 29.7
        },
        {
            "noteType": 1,
            "laneNum": 1,
            "startTime": 30.0,
            "endTime": 30.45
        },
        {
            "noteType": 1,
            "laneNum": 3,
            "startTime": 30.0,
            "endTime": 30.45
        },
        {
            "noteType": 0,
            "laneNum": 2,
            "startTime": 30.45,
            "endTime": 30.45
        },
        {
            "noteType": 0,
            "laneNum": 1,
            "startTime": 30.75,
            "endTime": 30.75
        },
        {
            "noteType": 0,
            "laneNum": 3,
            "startTime": 30.9,
            "endTime": 30.9
        },
        {
            "noteType": 1,
            "laneNum": 2,
            "startTime": 31.2,
            "endTime": 36.0
        },
        {
            "noteType": 0,
            "laneNum": 1,
            "startTime": 31.65,
            "endTime": 31.65
        },
        {
            "noteType": 0,
            "laneNum": 3,
            "startTime": 31.95,
            "endTime": 31.95
        },
        {
            "noteType": 0,
            "laneNum": 1,
            "startTime": 32.1,
            "endTime": 32.1
        },
        {
            "noteType": 0,
            "laneNum": 0,
            "startTime": 32.4,
            "endTime": 32.4
        },
        {
            "noteType": 1,
            "laneNum": 0,
            "startTime": 32.85,
            "endTime": 33.6
        },
        {
            "noteType": 0,
            "laneNum": 1,
            "startTime": 33.15,
            "endTime": 33.15
        },
        {
            "noteType": 0,
            "laneNum": 3,
            "startTime": 33.3,
            "endTime": 33.3
        },
        {
            "noteType": 0,
            "laneNum": 1,
            "startTime": 33.45,
            "endTime": 33.45
        },
        {
            "noteType": 0,
            "laneNum": 3,
            "startTime": 33.6,
            "endTime": 33.6
        },
        {
            "noteType": 0,
            "laneNum": 1,
            "startTime": 34.05,
            "endTime": 34.05
        },
        {
            "noteType": 0,
            "laneNum": 0,
            "startTime": 34.35,
            "endTime": 34.35
        },
        {
            "noteType": 0,
            "laneNum": 3,
            "startTime": 34.5,
            "endTime": 34.5
        },
        {
            "noteType": 1,
            "laneNum": 1,
            "startTime": 34.8,
            "endTime": 35.25
        },
        {
            "noteType": 1,
            "laneNum": 3,
            "startTime": 34.8,
            "endTime": 35.25
        },
        {
            "noteType": 0,
            "laneNum": 0,
            "startTime": 35.25,
            "endTime": 35.25
        },
        {
            "noteType": 0,
            "laneNum": 1,
            "startTime": 35.55,
            "endTime": 35.55
        },
        {
            "noteType": 0,
            "laneNum": 3,
            "startTime": 35.7,
            "endTime": 35.7
        },
        {
            "noteType": 1,
            "laneNum": 1,
            "startTime": 36.0,
            "endTime": 40.8
        },
        {
            "noteType": 0,
            "laneNum": 2,
            "startTime": 36.45,
            "endTime": 36.45
        },
        {
            "noteType": 0,
            "laneNum": 0,
            "startTime": 36.75,
            "endTime": 36.75
        },
        {
            "noteType": 0,
            "laneNum": 3,
            "startTime": 36.9,
            "endTime": 36.9
        },
        {
            "noteType": 0,
            "laneNum": 2,
            "startTime": 37.2,
            "endTime": 37.2
        },
        {
            "noteType": 1,
            "laneNum": 2,
            "startTime": 37.65,
            "endTime": 38.4
        },
        {
            "noteType": 0,
            "laneNum": 3,
            "startTime": 37.95,
            "endTime": 37.95
        },
        {
            "noteType": 0,
            "laneNum": 0,
            "startTime": 38.1,
            "endTime": 38.1
        },
        {
            "noteType": 0,
            "laneNum": 3,
            "startTime": 38.25,
            "endTime": 38.25
        },
        {
            "noteType": 0,
            "laneNum": 0,
            "startTime": 38.4,
            "endTime": 38.4
        },
        {
            "noteType": 1,
            "laneNum": 2,
            "startTime": 38.85,
            "endTime": 39.6
        },
        {
            "noteType": 0,
            "laneNum": 0,
            "startTime": 39.15,
            "endTime": 39.15
        },
        {
            "noteType": 0,
            "laneNum": 3,
            "startTime": 39.3,
            "endTime": 39.3
        },
        {
            "noteType": 0,
            "laneNum": 3,
            "startTime": 39.6,
            "endTime": 39.6
        },
        {
            "noteType": 1,
            "laneNum": 2,
            "startTime": 40.2,
            "endTime": 40.8
        },
        {
            "noteType": 1,
            "laneNum": 3,
            "startTime": 40.8,
            "endTime": 50.4
        },
        {
            "noteType": 0,
            "laneNum": 0,
            "startTime": 41.1,
            "endTime": 41.1
        },
        {
            "noteType": 0,
            "laneNum": 1,
            "startTime": 41.25,
            "endTime": 41.25
        },
        {
            "noteType": 0,
            "laneNum": 2,
            "startTime": 41.55,
            "endTime": 41.55
        },
        {
            "noteType": 0,
            "laneNum": 1,
            "startTime": 41.7,
            "endTime": 41.7
        },
        {
            "noteType": 0,
            "laneNum": 1,
            "startTime": 42.0,
            "endTime": 42.0
        },
        {
            "noteType": 1,
            "laneNum": 2,
            "startTime": 42.0,
            "endTime": 42.3
        },
        {
            "noteType": 0,
            "laneNum": 0,
            "startTime": 42.3,
            "endTime": 42.3
        },
        {
            "noteType": 1,
            "laneNum": 0,
            "startTime": 42.6,
            "endTime": 42.9
        },
        {
            "noteType": 0,
            "laneNum": 1,
            "startTime": 42.6,
            "endTime": 42.6
        },
        {
            "noteType": 0,
            "laneNum": 2,
            "startTime": 42.9,
            "endTime": 42.9
        },
        {
            "noteType": 0,
            "laneNum": 1,
            "startTime": 43.2,
            "endTime": 43.2
        },
        {
            "noteType": 0,
            "laneNum": 2,
            "startTime": 43.35,
            "endTime": 43.35
        },
        {
            "noteType": 0,
            "laneNum": 1,
            "startTime": 43.5,
            "endTime": 43.5
        },
        {
            "noteType": 0,
            "laneNum": 2,
            "startTime": 43.65,
            "endTime": 43.65
        },
        {
            "noteType": 0,
            "laneNum": 0,
            "startTime": 43.95,
            "endTime": 43.95
        },
        {
            "noteType": 0,
            "laneNum": 1,
            "startTime": 44.1,
            "endTime": 44.1
        },
        {
            "noteType": 0,
            "laneNum": 0,
            "startTime": 44.4,
            "endTime": 44.4
        },
        {
            "noteType": 1,
            "laneNum": 2,
            "startTime": 44.4,
            "endTime": 44.7
        },
        {
            "noteType": 0,
            "laneNum": 1,
            "startTime": 44.7,
            "endTime": 44.7
        },
        {
            "noteType": 0,
            "laneNum": 0,
            "startTime": 45.0,
            "endTime": 45.0
        },
        {
            "noteType": 1,
            "laneNum": 1,
            "startTime": 45.0,
            "endTime": 45.3
        },
        {
            "noteType": 0,
            "laneNum": 2,
            "startTime": 45.3,
            "endTime": 45.3
        },
        {
            "noteType": 0,
            "laneNum": 2,
            "startTime": 45.6,
            "endTime": 45.6
        },
        {
            "noteType": 0,
            "laneNum": 1,
            "startTime": 45.75,
            "endTime": 45.75
        },
        {
            "noteType": 0,
            "laneNum": 2,
            "startTime": 45.9,
            "endTime": 45.9
        },
        {
            "noteType": 0,
            "laneNum": 1,
            "startTime": 46.05,
            "endTime": 46.05
        },
        {
            "noteType": 0,
            "laneNum": 0,
            "startTime": 46.35,
            "endTime": 46.35
        },
        {
            "noteType": 0,
            "laneNum": 1,
            "startTime": 46.5,
            "endTime": 46.5
        },
        {
            "noteType": 1,
            "laneNum": 1,
            "startTime": 46.8,
            "endTime": 47.1
        },
        {
            "noteType": 0,
            "laneNum": 2,
            "startTime": 46.8,
            "endTime": 46.8
        },
        {
            "noteType": 0,
            "laneNum": 0,
            "startTime": 47.1,
            "endTime": 47.1
        },
        {
            "noteType": 1,
            "laneNum": 0,
            "startTime": 47.4,
            "endTime": 47.7
        },
        {
            "noteType": 0,
            "laneNum": 2,
            "startTime": 47.4,
            "endTime": 47.4
        },
        {
            "noteType": 0,
            "laneNum": 1,
            "startTime": 47.7,
            "endTime": 47.7
        },
        {
            "noteType": 0,
            "laneNum": 1,
            "startTime": 48.0,
            "endTime": 48.0
        },
        {
            "noteType": 0,
            "laneNum": 0,
            "startTime": 48.15,
            "endTime": 48.15
        },
        {
            "noteType": 0,
            "laneNum": 1,
            "startTime": 48.3,
            "endTime": 48.3
        },
        {
            "noteType": 0,
            "laneNum": 2,
            "startTime": 48.45,
            "endTime": 48.45
        },
        {
            "noteType": 0,
            "laneNum": 0,
            "startTime": 48.75,
            "endTime": 48.75
        },
        {
            "noteType": 0,
            "laneNum": 1,
            "startTime": 48.9,
            "endTime": 48.9
        },
        {
            "noteType": 0,
            "laneNum": 1,
            "startTime": 49.2,
            "endTime": 49.2
        },
        {
            "noteType": 1,
            "laneNum": 2,
            "startTime": 49.2,
            "endTime": 49.5
        },
        {
            "noteType": 0,
            "laneNum": 0,
            "startTime": 49.5,
            "endTime": 49.5
        },
        {
            "noteType": 1,
            "laneNum": 1,
            "startTime": 49.5,
            "endTime": 49.8
        },
        {
            "noteType": 0,
            "laneNum": 2,
            "startTime": 49.8,
            "endTime": 49.8
        },
        {
            "noteType": 1,
            "laneNum": 0,
            "startTime": 50.4,
            "endTime": 60.0
        },
        {
            "noteType": 0,
            "laneNum": 1,
            "startTime": 50.4,
            "endTime": 50.4
        },
        {
            "noteType": 0,
            "laneNum": 2,
            "startTime": 50.55,
            "endTime": 50.55
        },
        {
            "noteType": 0,
            "laneNum": 1,
            "startTime": 50.7,
            "endTime": 50.7
        },
        {
            "noteType": 0,
            "laneNum": 2,
            "startTime": 50.85,
            "endTime": 50.85
        },
        {
            "noteType": 0,
            "laneNum": 3,
            "startTime": 51.15,
            "endTime": 51.15
        },
        {
            "noteType": 0,
            "laneNum": 1,
            "startTime": 51.3,
            "endTime": 51.3
        },
        {
            "noteType": 1,
            "laneNum": 2,
            "startTime": 51.6,
            "endTime": 52.8
        },
        {
            "noteType": 0,
            "laneNum": 3,
            "startTime": 51.6,
            "endTime": 51.6
        },
        {
            "noteType": 0,
            "laneNum": 1,
            "startTime": 51.9,
            "endTime": 51.9
        },
        {
            "noteType": 0,
            "laneNum": 3,
            "startTime": 52.2,
            "endTime": 52.2
        },
        {
            "noteType": 0,
            "laneNum": 1,
            "startTime": 52.5,
            "endTime": 52.5
        },
        {
            "noteType": 0,
            "laneNum": 3,
            "startTime": 52.8,
            "endTime": 52.8
        },
        {
            "noteType": 0,
            "laneNum": 1,
            "startTime": 52.95,
            "endTime": 52.95
        },
        {
            "noteType": 0,
            "laneNum": 3,
            "startTime": 53.1,
            "endTime": 53.1
        },
        {
            "noteType": 0,
            "laneNum": 1,
            "startTime": 53.25,
            "endTime": 53.25
        },
        {
            "noteType": 0,
            "laneNum": 2,
            "startTime": 53.55,
            "endTime": 53.55
        },
        {
            "noteType": 0,
            "laneNum": 3,
            "startTime": 53.7,
            "endTime": 53.7
        },
        {
            "noteType": 1,
            "laneNum": 1,
            "startTime": 54.0,
            "endTime": 55.2
        },
        {
            "noteType": 0,
            "laneNum": 2,
            "startTime": 54.0,
            "endTime": 54.0
        },
        {
            "noteType": 0,
            "laneNum": 3,
            "startTime": 54.3,
            "endTime": 54.3
        },
        {
            "noteType": 0,
            "laneNum": 2,
            "startTime": 54.6,
            "endTime": 54.6
        },
        {
            "noteType": 0,
            "laneNum": 3,
            "startTime": 54.9,
            "endTime": 54.9
        },
        {
            "noteType": 0,
            "laneNum": 2,
            "startTime": 55.2,
            "endTime": 55.2
        },
        {
            "noteType": 0,
            "laneNum": 3,
            "startTime": 55.35,
            "endTime": 55.35
        },
        {
            "noteType": 0,
            "laneNum": 2,
            "startTime": 55.5,
            "endTime": 55.5
        },
        {
            "noteType": 0,
            "laneNum": 3,
            "startTime": 55.65,
            "endTime": 55.65
        },
        {
            "noteType": 0,
            "laneNum": 2,
            "startTime": 55.95,
            "endTime": 55.95
        },
        {
            "noteType": 0,
            "laneNum": 1,
            "startTime": 56.1,
            "endTime": 56.1
        },
        {
            "noteType": 0,
            "laneNum": 2,
            "startTime": 56.4,
            "endTime": 56.4
        },
        {
            "noteType": 1,
            "laneNum": 3,
            "startTime": 56.4,
            "endTime": 57.6
        },
        {
            "noteType": 0,
            "laneNum": 1,
            "startTime": 56.7,
            "endTime": 56.7
        },
        {
            "noteType": 0,
            "laneNum": 2,
            "startTime": 57.0,
            "endTime": 57.0
        },
        {
            "noteType": 0,
            "laneNum": 1,
            "startTime": 57.3,
            "endTime": 57.3
        },
        {
            "noteType": 0,
            "laneNum": 2,
            "startTime": 57.6,
            "endTime": 57.6
        },
        {
            "noteType": 0,
            "laneNum": 1,
            "startTime": 57.75,
            "endTime": 57.75
        },
        {
            "noteType": 0,
            "laneNum": 2,
            "startTime": 57.9,
            "endTime": 57.9
        },
        {
            "noteType": 0,
            "laneNum": 1,
            "startTime": 58.05,
            "endTime": 58.05
        },
        {
            "noteType": 0,
            "laneNum": 3,
            "startTime": 58.35,
            "endTime": 58.35
        },
        {
            "noteType": 0,
            "laneNum": 1,
            "startTime": 58.5,
            "endTime": 58.5
        },
        {
            "noteType": 0,
            "laneNum": 1,
            "startTime": 58.8,
            "endTime": 58.8
        },
        {
            "noteType": 1,
            "laneNum": 2,
            "startTime": 58.8,
            "endTime": 60.0
        },
        {
            "noteType": 0,
            "laneNum": 3,
            "startTime": 59.1,
            "endTime": 59.1
        },
        {
            "noteType": 0,
            "laneNum": 1,
            "startTime": 59.4,
            "endTime": 59.4
        },
        {
            "noteType": 0,
            "laneNum": 3,
            "startTime": 59.7,
            "endTime": 59.7
        },
        {
            "noteType": 0,
            "laneNum": 1,
            "startTime": 60.0,
            "endTime": 60.0
        },
        {
            "noteType": 0,
            "laneNum": 3,
            "startTime": 60.15,
            "endTime": 60.15
        },
        {
            "noteType": 0,
            "laneNum": 1,
            "startTime": 60.3,
            "endTime": 60.3
        },
        {
            "noteType": 0,
            "laneNum": 3,
            "startTime": 60.45,
            "endTime": 60.45
        },
        {
            "noteType": 0,
            "laneNum": 2,
            "startTime": 60.6,
            "endTime": 60.6
        },
        {
            "noteType": 0,
            "laneNum": 1,
            "startTime": 60.75,
            "endTime": 60.75
        },
        {
            "noteType": 0,
            "laneNum": 3,
            "startTime": 60.9,
            "endTime": 60.9
        },
        {
            "noteType": 0,
            "laneNum": 0,
            "startTime": 61.05,
            "endTime": 61.05
        },
        {
            "noteType": 0,
            "laneNum": 2,
            "startTime": 61.35,
            "endTime": 61.35
        },
        {
            "noteType": 0,
            "laneNum": 1,
            "startTime": 61.5,
            "endTime": 61.5
        },
        {
            "noteType": 0,
            "laneNum": 2,
            "startTime": 61.65,
            "endTime": 61.65
        },
        {
            "noteType": 0,
            "laneNum": 1,
            "startTime": 61.8,
            "endTime": 61.8
        },
        {
            "noteType": 0,
            "laneNum": 3,
            "startTime": 61.95,
            "endTime": 61.95
        },
        {
            "noteType": 0,
            "laneNum": 0,
            "startTime": 62.1,
            "endTime": 62.1
        },
        {
            "noteType": 1,
            "laneNum": 0,
            "startTime": 62.4,
            "endTime": 63.6
        },
        {
            "noteType": 0,
            "laneNum": 1,
            "startTime": 62.4,
            "endTime": 62.4
        },
        {
            "noteType": 0,
            "laneNum": 3,
            "startTime": 62.55,
            "endTime": 62.55
        },
        {
            "noteType": 0,
            "laneNum": 1,
            "startTime": 62.7,
            "endTime": 62.7
        },
        {
            "noteType": 0,
            "laneNum": 3,
            "startTime": 62.85,
            "endTime": 62.85
        },
        {
            "noteType": 0,
            "laneNum": 2,
            "startTime": 63.0,
            "endTime": 63.0
        },
        {
            "noteType": 0,
            "laneNum": 1,
            "startTime": 63.15,
            "endTime": 63.15
        },
        {
            "noteType": 0,
            "laneNum": 2,
            "startTime": 63.3,
            "endTime": 63.3
        },
        {
            "noteType": 0,
            "laneNum": 1,
            "startTime": 63.45,
            "endTime": 63.45
        },
        {
            "noteType": 0,
            "laneNum": 2,
            "startTime": 63.75,
            "endTime": 63.75
        },
        {
            "noteType": 0,
            "laneNum": 1,
            "startTime": 63.9,
            "endTime": 63.9
        },
        {
            "noteType": 0,
            "laneNum": 2,
            "startTime": 64.05,
            "endTime": 64.05
        },
        {
            "noteType": 0,
            "laneNum": 1,
            "startTime": 64.2,
            "endTime": 64.2
        },
        {
            "noteType": 0,
            "laneNum": 3,
            "startTime": 64.35,
            "endTime": 64.35
        },
        {
            "noteType": 0,
            "laneNum": 0,
            "startTime": 64.5,
            "endTime": 64.5
        },
        {
            "noteType": 0,
            "laneNum": 2,
            "startTime": 64.8,
            "endTime": 64.8
        },
        {
            "noteType": 1,
            "laneNum": 3,
            "startTime": 64.8,
            "endTime": 66.0
        },
        {
            "noteType": 0,
            "laneNum": 0,
            "startTime": 64.95,
            "endTime": 64.95
        },
        {
            "noteType": 0,
            "laneNum": 2,
            "startTime": 65.1,
            "endTime": 65.1
        },
        {
            "noteType": 0,
            "laneNum": 0,
            "startTime": 65.25,
            "endTime": 65.25
        },
        {
            "noteType": 0,
            "laneNum": 2,
            "startTime": 65.4,
            "endTime": 65.4
        },
        {
            "noteType": 0,
            "laneNum": 1,
            "startTime": 65.55,
            "endTime": 65.55
        },
        {
            "noteType": 0,
            "laneNum": 2,
            "startTime": 65.7,
            "endTime": 65.7
        },
        {
            "noteType": 0,
            "laneNum": 1,
            "startTime": 65.85,
            "endTime": 65.85
        },
        {
            "noteType": 0,
            "laneNum": 0,
            "startTime": 66.15,
            "endTime": 66.15
        },
        {
            "noteType": 0,
            "laneNum": 3,
            "startTime": 66.3,
            "endTime": 66.3
        },
        {
            "noteType": 0,
            "laneNum": 0,
            "startTime": 66.45,
            "endTime": 66.45
        },
        {
            "noteType": 0,
            "laneNum": 3,
            "startTime": 66.6,
            "endTime": 66.6
        },
        {
            "noteType": 0,
            "laneNum": 0,
            "startTime": 66.75,
            "endTime": 66.75
        },
        {
            "noteType": 0,
            "laneNum": 3,
            "startTime": 66.9,
            "endTime": 66.9
        },
        {
            "noteType": 0,
            "laneNum": 2,
            "startTime": 67.2,
            "endTime": 67.2
        },
        {
            "noteType": 1,
            "laneNum": 3,
            "startTime": 67.2,
            "endTime": 68.4
        },
        {
            "noteType": 0,
            "laneNum": 0,
            "startTime": 67.35,
            "endTime": 67.35
        },
        {
            "noteType": 0,
            "laneNum": 2,
            "startTime": 67.5,
            "endTime": 67.5
        },
        {
            "noteType": 0,
            "laneNum": 0,
            "startTime": 67.65,
            "endTime": 67.65
        },
        {
            "noteType": 0,
            "laneNum": 2,
            "startTime": 67.8,
            "endTime": 67.8
        },
        {
            "noteType": 0,
            "laneNum": 1,
            "startTime": 67.95,
            "endTime": 67.95
        },
        {
            "noteType": 0,
            "laneNum": 2,
            "startTime": 68.1,
            "endTime": 68.1
        },
        {
            "noteType": 0,
            "laneNum": 1,
            "startTime": 68.25,
            "endTime": 68.25
        },
        {
            "noteType": 0,
            "laneNum": 0,
            "startTime": 68.55,
            "endTime": 68.55
        },
        {
            "noteType": 0,
            "laneNum": 3,
            "startTime": 68.7,
            "endTime": 68.7
        },
        {
            "noteType": 0,
            "laneNum": 0,
            "startTime": 68.85,
            "endTime": 68.85
        },
        {
            "noteType": 0,
            "laneNum": 3,
            "startTime": 69.0,
            "endTime": 69.0
        },
        {
            "noteType": 0,
            "laneNum": 0,
            "startTime": 69.15,
            "endTime": 69.15
        },
        {
            "noteType": 0,
            "laneNum": 3,
            "startTime": 69.3,
            "endTime": 69.3
        },
        {
            "noteType": 0,
            "laneNum": 0,
            "startTime": 69.6,
            "endTime": 69.6
        },
        {
            "noteType": 1,
            "laneNum": 2,
            "startTime": 69.6,
            "endTime": 74.4
        },
        {
            "noteType": 0,
            "laneNum": 3,
            "startTime": 69.75,
            "endTime": 69.75
        },
        {
            "noteType": 0,
            "laneNum": 0,
            "startTime": 69.9,
            "endTime": 69.9
        },
        {
            "noteType": 0,
            "laneNum": 3,
            "startTime": 70.05,
            "endTime": 70.05
        },
        {
            "noteType": 0,
            "laneNum": 1,
            "startTime": 70.2,
            "endTime": 70.2
        },
        {
            "noteType": 0,
            "laneNum": 0,
            "startTime": 70.35,
            "endTime": 70.35
        },
        {
            "noteType": 0,
            "laneNum": 1,
            "startTime": 70.5,
            "endTime": 70.5
        },
        {
            "noteType": 0,
            "laneNum": 0,
            "startTime": 70.65,
            "endTime": 70.65
        },
        {
            "noteType": 0,
            "laneNum": 1,
            "startTime": 70.95,
            "endTime": 70.95
        },
        {
            "noteType": 0,
            "laneNum": 3,
            "startTime": 71.1,
            "endTime": 71.1
        },
        {
            "noteType": 0,
            "laneNum": 1,
            "startTime": 71.25,
            "endTime": 71.25
        },
        {
            "noteType": 0,
            "laneNum": 3,
            "startTime": 71.4,
            "endTime": 71.4
        },
        {
            "noteType": 0,
            "laneNum": 0,
            "startTime": 71.55,
            "endTime": 71.55
        },
        {
            "noteType": 0,
            "laneNum": 1,
            "startTime": 71.7,
            "endTime": 71.7
        },
        {
            "noteType": 0,
            "laneNum": 0,
            "startTime": 72.0,
            "endTime": 72.0
        },
        {
            "noteType": 0,
            "laneNum": 3,
            "startTime": 72.15,
            "endTime": 72.15
        },
        {
            "noteType": 0,
            "laneNum": 0,
            "startTime": 72.3,
            "endTime": 72.3
        },
        {
            "noteType": 0,
            "laneNum": 3,
            "startTime": 72.45,
            "endTime": 72.45
        },
        {
            "noteType": 0,
            "laneNum": 1,
            "startTime": 72.6,
            "endTime": 72.6
        },
        {
            "noteType": 0,
            "laneNum": 3,
            "startTime": 72.75,
            "endTime": 72.75
        },
        {
            "noteType": 0,
            "laneNum": 1,
            "startTime": 72.9,
            "endTime": 72.9
        },
        {
            "noteType": 0,
            "laneNum": 3,
            "startTime": 73.05,
            "endTime": 73.05
        },
        {
            "noteType": 0,
            "laneNum": 1,
            "startTime": 73.35,
            "endTime": 73.35
        },
        {
            "noteType": 0,
            "laneNum": 3,
            "startTime": 73.5,
            "endTime": 73.5
        },
        {
            "noteType": 0,
            "laneNum": 1,
            "startTime": 73.65,
            "endTime": 73.65
        },
        {
            "noteType": 0,
            "laneNum": 3,
            "startTime": 73.8,
            "endTime": 73.8
        },
        {
            "noteType": 0,
            "laneNum": 1,
            "startTime": 73.95,
            "endTime": 73.95
        },
        {
            "noteType": 0,
            "laneNum": 0,
            "startTime": 74.1,
            "endTime": 74.1
        },
        {
            "noteType": 0,
            "laneNum": 0,
            "startTime": 74.4,
            "endTime": 74.4
        },
        {
            "noteType": 1,
            "laneNum": 1,
            "startTime": 74.4,
            "endTime": 79.2
        },
        {
            "noteType": 0,
            "laneNum": 3,
            "startTime": 74.55,
            "endTime": 74.55
        },
        {
            "noteType": 0,
            "laneNum": 0,
            "startTime": 74.7,
            "endTime": 74.7
        },
        {
            "noteType": 0,
            "laneNum": 3,
            "startTime": 74.85,
            "endTime": 74.85
        },
        {
            "noteType": 0,
            "laneNum": 2,
            "startTime": 75.0,
            "endTime": 75.0
        },
        {
            "noteType": 0,
            "laneNum": 3,
            "startTime": 75.15,
            "endTime": 75.15
        },
        {
            "noteType": 0,
            "laneNum": 2,
            "startTime": 75.3,
            "endTime": 75.3
        },
        {
            "noteType": 0,
            "laneNum": 3,
            "startTime": 75.45,
            "endTime": 75.45
        },
        {
            "noteType": 0,
            "laneNum": 2,
            "startTime": 75.75,
            "endTime": 75.75
        },
        {
            "noteType": 0,
            "laneNum": 0,
            "startTime": 75.9,
            "endTime": 75.9
        },
        {
            "noteType": 0,
            "laneNum": 2,
            "startTime": 76.05,
            "endTime": 76.05
        },
        {
            "noteType": 0,
            "laneNum": 0,
            "startTime": 76.2,
            "endTime": 76.2
        },
        {
            "noteType": 0,
            "laneNum": 3,
            "startTime": 76.35,
            "endTime": 76.35
        },
        {
            "noteType": 0,
            "laneNum": 2,
            "startTime": 76.5,
            "endTime": 76.5
        },
        {
            "noteType": 0,
            "laneNum": 0,
            "startTime": 76.8,
            "endTime": 76.8
        },
        {
            "noteType": 0,
            "laneNum": 3,
            "startTime": 76.95,
            "endTime": 76.95
        },
        {
            "noteType": 0,
            "laneNum": 0,
            "startTime": 77.1,
            "endTime": 77.1
        },
        {
            "noteType": 0,
            "laneNum": 3,
            "startTime": 77.25,
            "endTime": 77.25
        },
        {
            "noteType": 0,
            "laneNum": 2,
            "startTime": 77.4,
            "endTime": 77.4
        },
        {
            "noteType": 0,
            "laneNum": 3,
            "startTime": 77.55,
            "endTime": 77.55
        },
        {
            "noteType": 0,
            "laneNum": 2,
            "startTime": 77.7,
            "endTime": 77.7
        },
        {
            "noteType": 0,
            "laneNum": 3,
            "startTime": 77.85,
            "endTime": 77.85
        },
        {
            "noteType": 0,
            "laneNum": 2,
            "startTime": 78.15,
            "endTime": 78.15
        },
        {
            "noteType": 0,
            "laneNum": 3,
            "startTime": 78.3,
            "endTime": 78.3
        },
        {
            "noteType": 0,
            "laneNum": 2,
            "startTime": 78.45,
            "endTime": 78.45
        },
        {
            "noteType": 0,
            "laneNum": 3,
            "startTime": 78.6,
            "endTime": 78.6
        },
        {
            "noteType": 0,
            "laneNum": 2,
            "startTime": 78.75,
            "endTime": 78.75
        },
        {
            "noteType": 0,
            "laneNum": 3,
            "startTime": 78.9,
            "endTime": 78.9
        },
        {
            "noteType": 0,
            "laneNum": 0,
            "startTime": 79.2,
            "endTime": 79.2
        },
        {
            "noteType": 0,
            "laneNum": 2,
            "startTime": 79.2,
            "endTime": 79.2
        },
        {
            "noteType": 0,
            "laneNum": 2,
            "startTime": 79.5,
            "endTime": 79.5
        },
        {
            "noteType": 0,
            "laneNum": 0,
            "startTime": 79.65,
            "endTime": 79.65
        },
        {
            "noteType": 0,
            "laneNum": 2,
            "startTime": 79.8,
            "endTime": 79.8
        },
        {
            "noteType": 0,
            "laneNum": 3,
            "startTime": 79.8,
            "endTime": 79.8
        },
        {
            "noteType": 0,
            "laneNum": 0,
            "startTime": 79.95,
            "endTime": 79.95
        },
        {
            "noteType": 0,
            "laneNum": 1,
            "startTime": 80.1,
            "endTime": 80.1
        },
        {
            "noteType": 0,
            "laneNum": 2,
            "startTime": 80.1,
            "endTime": 80.1
        },
        {
            "noteType": 0,
            "laneNum": 0,
            "startTime": 80.4,
            "endTime": 80.4
        },
        {
            "noteType": 0,
            "laneNum": 2,
            "startTime": 80.4,
            "endTime": 80.4
        },
        {
            "noteType": 0,
            "laneNum": 2,
            "startTime": 80.7,
            "endTime": 80.7
        },
        {
            "noteType": 0,
            "laneNum": 0,
            "startTime": 80.85,
            "endTime": 80.85
        },
        {
            "noteType": 0,
            "laneNum": 2,
            "startTime": 81.0,
            "endTime": 81.0
        },
        {
            "noteType": 0,
            "laneNum": 3,
            "startTime": 81.0,
            "endTime": 81.0
        },
        {
            "noteType": 0,
            "laneNum": 1,
            "startTime": 81.15,
            "endTime": 81.15
        },
        {
            "noteType": 0,
            "laneNum": 0,
            "startTime": 81.3,
            "endTime": 81.3
        },
        {
            "noteType": 0,
            "laneNum": 2,
            "startTime": 81.3,
            "endTime": 81.3
        },
        {
            "noteType": 0,
            "laneNum": 1,
            "startTime": 81.45,
            "endTime": 81.45
        },
        {
            "noteType": 0,
            "laneNum": 0,
            "startTime": 81.6,
            "endTime": 81.6
        },
        {
            "noteType": 0,
            "laneNum": 2,
            "startTime": 81.6,
            "endTime": 81.6
        },
        {
            "noteType": 0,
            "laneNum": 2,
            "startTime": 81.9,
            "endTime": 81.9
        },
        {
            "noteType": 0,
            "laneNum": 0,
            "startTime": 82.05,
            "endTime": 82.05
        },
        {
            "noteType": 0,
            "laneNum": 2,
            "startTime": 82.2,
            "endTime": 82.2
        },
        {
            "noteType": 0,
            "laneNum": 3,
            "startTime": 82.2,
            "endTime": 82.2
        },
        {
            "noteType": 0,
            "laneNum": 0,
            "startTime": 82.35,
            "endTime": 82.35
        },
        {
            "noteType": 0,
            "laneNum": 1,
            "startTime": 82.5,
            "endTime": 82.5
        },
        {
            "noteType": 0,
            "laneNum": 2,
            "startTime": 82.5,
            "endTime": 82.5
        },
        {
            "noteType": 0,
            "laneNum": 0,
            "startTime": 82.8,
            "endTime": 82.8
        },
        {
            "noteType": 0,
            "laneNum": 2,
            "startTime": 82.8,
            "endTime": 82.8
        },
        {
            "noteType": 0,
            "laneNum": 2,
            "startTime": 83.1,
            "endTime": 83.1
        },
        {
            "noteType": 0,
            "laneNum": 0,
            "startTime": 83.25,
            "endTime": 83.25
        },
        {
            "noteType": 0,
            "laneNum": 2,
            "startTime": 83.4,
            "endTime": 83.4
        },
        {
            "noteType": 0,
            "laneNum": 3,
            "startTime": 83.4,
            "endTime": 83.4
        },
        {
            "noteType": 0,
            "laneNum": 0,
            "startTime": 83.55,
            "endTime": 83.55
        },
        {
            "noteType": 0,
            "laneNum": 1,
            "startTime": 83.7,
            "endTime": 83.7
        },
        {
            "noteType": 0,
            "laneNum": 2,
            "startTime": 83.7,
            "endTime": 83.7
        },
        {
            "noteType": 0,
            "laneNum": 0,
            "startTime": 84.0,
            "endTime": 84.0
        },
        {
            "noteType": 0,
            "laneNum": 3,
            "startTime": 84.0,
            "endTime": 84.0
        },
        {
            "noteType": 0,
            "laneNum": 3,
            "startTime": 84.3,
            "endTime": 84.3
        },
        {
            "noteType": 0,
            "laneNum": 0,
            "startTime": 84.45,
            "endTime": 84.45
        },
        {
            "noteType": 0,
            "laneNum": 2,
            "startTime": 84.6,
            "endTime": 84.6
        },
        {
            "noteType": 0,
            "laneNum": 3,
            "startTime": 84.6,
            "endTime": 84.6
        },
        {
            "noteType": 0,
            "laneNum": 0,
            "startTime": 84.75,
            "endTime": 84.75
        },
        {
            "noteType": 0,
            "laneNum": 1,
            "startTime": 84.9,
            "endTime": 84.9
        },
        {
            "noteType": 0,
            "laneNum": 3,
            "startTime": 84.9,
            "endTime": 84.9
        },
        {
            "noteType": 0,
            "laneNum": 0,
            "startTime": 85.2,
            "endTime": 85.2
        },
        {
            "noteType": 0,
            "laneNum": 3,
            "startTime": 85.2,
            "endTime": 85.2
        },
        {
            "noteType": 0,
            "laneNum": 3,
            "startTime": 85.5,
            "endTime": 85.5
        },
        {
            "noteType": 0,
            "laneNum": 0,
            "startTime": 85.65,
            "endTime": 85.65
        },
        {
            "noteType": 0,
            "laneNum": 2,
            "startTime": 85.8,
            "endTime": 85.8
        },
        {
            "noteType": 0,
            "laneNum": 3,
            "startTime": 85.8,
            "endTime": 85.8
        },
        {
            "noteType": 0,
            "laneNum": 1,
            "startTime": 85.95,
            "endTime": 85.95
        },
        {
            "noteType": 0,
            "laneNum": 0,
            "startTime": 86.1,
            "endTime": 86.1
        },
        {
            "noteType": 0,
            "laneNum": 3,
            "startTime": 86.1,
            "endTime": 86.1
        },
        {
            "noteType": 0,
            "laneNum": 1,
            "startTime": 86.25,
            "endTime": 86.25
        },
        {
            "noteType": 0,
            "laneNum": 0,
            "startTime": 86.4,
            "endTime": 86.4
        },
        {
            "noteType": 0,
            "laneNum": 3,
            "startTime": 86.4,
            "endTime": 86.4
        },
        {
            "noteType": 0,
            "laneNum": 3,
            "startTime": 86.7,
            "endTime": 86.7
        },
        {
            "noteType": 0,
            "laneNum": 0,
            "startTime": 86.85,
            "endTime": 86.85
        },
        {
            "noteType": 0,
            "laneNum": 2,
            "startTime": 87.0,
            "endTime": 87.0
        },
        {
            "noteType": 0,
            "laneNum": 3,
            "startTime": 87.0,
            "endTime": 87.0
        },
        {
            "noteType": 0,
            "laneNum": 0,
            "startTime": 87.15,
            "endTime": 87.15
        },
        {
            "noteType": 0,
            "laneNum": 1,
            "startTime": 87.3,
            "endTime": 87.3
        },
        {
            "noteType": 0,
            "laneNum": 3,
            "startTime": 87.3,
            "endTime": 87.3
        },
        {
            "noteType": 0,
            "laneNum": 0,
            "startTime": 87.6,
            "endTime": 87.6
        },
        {
            "noteType": 0,
            "laneNum": 3,
            "startTime": 87.6,
            "endTime": 87.6
        },
        {
            "noteType": 0,
            "laneNum": 3,
            "startTime": 87.9,
            "endTime": 87.9
        },
        {
            "noteType": 0,
            "laneNum": 0,
            "startTime": 88.05,
            "endTime": 88.05
        },
        {
            "noteType": 0,
            "laneNum": 2,
            "startTime": 88.2,
            "endTime": 88.2
        },
        {
            "noteType": 0,
            "laneNum": 3,
            "startTime": 88.2,
            "endTime": 88.2
        },
        {
            "noteType": 0,
            "laneNum": 0,
            "startTime": 88.35,
            "endTime": 88.35
        },
        {
            "noteType": 0,
            "laneNum": 1,
            "startTime": 88.5,
            "endTime": 88.5
        },
        {
            "noteType": 0,
            "laneNum": 3,
            "startTime": 88.5,
            "endTime": 88.5
        },
        {
            "noteType": 0,
            "laneNum": 0,
            "startTime": 88.8,
            "endTime": 88.8
        },
        {
            "noteType": 0,
            "laneNum": 2,
            "startTime": 88.8,
            "endTime": 88.8
        },
        {
            "noteType": 0,
            "laneNum": 2,
            "startTime": 89.1,
            "endTime": 89.1
        },
        {
            "noteType": 0,
            "laneNum": 0,
            "startTime": 89.25,
            "endTime": 89.25
        },
        {
            "noteType": 0,
            "laneNum": 2,
            "startTime": 89.4,
            "endTime": 89.4
        },
        {
            "noteType": 0,
            "laneNum": 3,
            "startTime": 89.4,
            "endTime": 89.4
        },
        {
            "noteType": 0,
            "laneNum": 0,
            "startTime": 89.55,
            "endTime": 89.55
        },
        {
            "noteType": 0,
            "laneNum": 1,
            "startTime": 89.7,
            "endTime": 89.7
        },
        {
            "noteType": 0,
            "laneNum": 2,
            "startTime": 89.7,
            "endTime": 89.7
        },
        {
            "noteType": 0,
            "laneNum": 0,
            "startTime": 90.0,
            "endTime": 90.0
        },
        {
            "noteType": 0,
            "laneNum": 2,
            "startTime": 90.0,
            "endTime": 90.0
        },
        {
            "noteType": 0,
            "laneNum": 2,
            "startTime": 90.3,
            "endTime": 90.3
        },
        {
            "noteType": 0,
            "laneNum": 0,
            "startTime": 90.45,
            "endTime": 90.45
        },
        {
            "noteType": 0,
            "laneNum": 2,
            "startTime": 90.6,
            "endTime": 90.6
        },
        {
            "noteType": 0,
            "laneNum": 3,
            "startTime": 90.6,
            "endTime": 90.6
        },
        {
            "noteType": 0,
            "laneNum": 1,
            "startTime": 90.75,
            "endTime": 90.75
        },
        {
            "noteType": 0,
            "laneNum": 0,
            "startTime": 90.9,
            "endTime": 90.9
        },
        {
            "noteType": 0,
            "laneNum": 2,
            "startTime": 90.9,
            "endTime": 90.9
        },
        {
            "noteType": 0,
            "laneNum": 1,
            "startTime": 91.05,
            "endTime": 91.05
        },
        {
            "noteType": 0,
            "laneNum": 0,
            "startTime": 91.2,
            "endTime": 91.2
        },
        {
            "noteType": 0,
            "laneNum": 2,
            "startTime": 91.2,
            "endTime": 91.2
        },
        {
            "noteType": 0,
            "laneNum": 2,
            "startTime": 91.5,
            "endTime": 91.5
        },
        {
            "noteType": 0,
            "laneNum": 0,
            "startTime": 91.65,
            "endTime": 91.65
        },
        {
            "noteType": 0,
            "laneNum": 2,
            "startTime": 91.8,
            "endTime": 91.8
        },
        {
            "noteType": 0,
            "laneNum": 3,
            "startTime": 91.8,
            "endTime": 91.8
        },
        {
            "noteType": 0,
            "laneNum": 0,
            "startTime": 91.95,
            "endTime": 91.95
        },
        {
            "noteType": 0,
            "laneNum": 1,
            "startTime": 92.1,
            "endTime": 92.1
        },
        {
            "noteType": 0,
            "laneNum": 2,
            "startTime": 92.1,
            "endTime": 92.1
        },
        {
            "noteType": 0,
            "laneNum": 0,
            "startTime": 92.4,
            "endTime": 92.4
        },
        {
            "noteType": 0,
            "laneNum": 2,
            "startTime": 92.4,
            "endTime": 92.4
        },
        {
            "noteType": 0,
            "laneNum": 2,
            "startTime": 92.7,
            "endTime": 92.7
        },
        {
            "noteType": 0,
            "laneNum": 0,
            "startTime": 92.85,
            "endTime": 92.85
        },
        {
            "noteType": 0,
            "laneNum": 2,
            "startTime": 93.0,
            "endTime": 93.0
        },
        {
            "noteType": 0,
            "laneNum": 3,
            "startTime": 93.0,
            "endTime": 93.0
        },
        {
            "noteType": 0,
            "laneNum": 0,
            "startTime": 93.15,
            "endTime": 93.15
        },
        {
            "noteType": 0,
            "laneNum": 1,
            "startTime": 93.3,
            "endTime": 93.3
        },
        {
            "noteType": 0,
            "laneNum": 2,
            "startTime": 93.3,
            "endTime": 93.3
        },
        {
            "noteType": 0,
            "laneNum": 0,
            "startTime": 93.6,
            "endTime": 93.6
        },
        {
            "noteType": 0,
            "laneNum": 3,
            "startTime": 93.6,
            "endTime": 93.6
        },
        {
            "noteType": 0,
            "laneNum": 3,
            "startTime": 93.9,
            "endTime": 93.9
        },
        {
            "noteType": 0,
            "laneNum": 0,
            "startTime": 94.05,
            "endTime": 94.05
        },
        {
            "noteType": 0,
            "laneNum": 2,
            "startTime": 94.2,
            "endTime": 94.2
        },
        {
            "noteType": 0,
            "laneNum": 3,
            "startTime": 94.2,
            "endTime": 94.2
        },
        {
            "noteType": 0,
            "laneNum": 0,
            "startTime": 94.35,
            "endTime": 94.35
        },
        {
            "noteType": 0,
            "laneNum": 1,
            "startTime": 94.5,
            "endTime": 94.5
        },
        {
            "noteType": 0,
            "laneNum": 3,
            "startTime": 94.5,
            "endTime": 94.5
        },
        {
            "noteType": 0,
            "laneNum": 0,
            "startTime": 94.8,
            "endTime": 94.8
        },
        {
            "noteType": 0,
            "laneNum": 3,
            "startTime": 94.8,
            "endTime": 94.8
        },
        {
            "noteType": 0,
            "laneNum": 3,
            "startTime": 95.1,
            "endTime": 95.1
        },
        {
            "noteType": 0,
            "laneNum": 0,
            "startTime": 95.25,
            "endTime": 95.25
        },
        {
            "noteType": 0,
            "laneNum": 2,
            "startTime": 95.4,
            "endTime": 95.4
        },
        {
            "noteType": 0,
            "laneNum": 3,
            "startTime": 95.4,
            "endTime": 95.4
        },
        {
            "noteType": 0,
            "laneNum": 1,
            "startTime": 95.55,
            "endTime": 95.55
        },
        {
            "noteType": 0,
            "laneNum": 0,
            "startTime": 95.7,
            "endTime": 95.7
        },
        {
            "noteType": 0,
            "laneNum": 3,
            "startTime": 95.7,
            "endTime": 95.7
        },
        {
            "noteType": 0,
            "laneNum": 1,
            "startTime": 95.85,
            "endTime": 95.85
        },
        {
            "noteType": 0,
            "laneNum": 0,
            "startTime": 96.0,
            "endTime": 96.0
        },
        {
            "noteType": 0,
            "laneNum": 3,
            "startTime": 96.0,
            "endTime": 96.0
        },
        {
            "noteType": 0,
            "laneNum": 3,
            "startTime": 96.3,
            "endTime": 96.3
        },
        {
            "noteType": 0,
            "laneNum": 0,
            "startTime": 96.45,
            "endTime": 96.45
        },
        {
            "noteType": 0,
            "laneNum": 2,
            "startTime": 96.6,
            "endTime": 96.6
        },
        {
            "noteType": 0,
            "laneNum": 3,
            "startTime": 96.6,
            "endTime": 96.6
        },
        {
            "noteType": 0,
            "laneNum": 0,
            "startTime": 96.75,
            "endTime": 96.75
        },
        {
            "noteType": 0,
            "laneNum": 1,
            "startTime": 96.9,
            "endTime": 96.9
        },
        {
            "noteType": 0,
            "laneNum": 3,
            "startTime": 96.9,
            "endTime": 96.9
        },
        {
            "noteType": 0,
            "laneNum": 0,
            "startTime": 97.2,
            "endTime": 97.2
        },
        {
            "noteType": 0,
            "laneNum": 3,
            "startTime": 97.2,
            "endTime": 97.2
        },
        {
            "noteType": 0,
            "laneNum": 3,
            "startTime": 97.5,
            "endTime": 97.5
        },
        {
            "noteType": 0,
            "laneNum": 0,
            "startTime": 97.65,
            "endTime": 97.65
        },
        {
            "noteType": 0,
            "laneNum": 2,
            "startTime": 97.8,
            "endTime": 97.8
        },
        {
            "noteType": 0,
            "laneNum": 3,
            "startTime": 97.8,
            "endTime": 97.8
        },
        {
            "noteType": 0,
            "laneNum": 0,
            "startTime": 97.95,
            "endTime": 97.95
        },
        {
            "noteType": 0,
            "laneNum": 1,
            "startTime": 98.1,
            "endTime": 98.1
        },
        {
            "noteType": 0,
            "laneNum": 3,
            "startTime": 98.1,
            "endTime": 98.1
        },
        {
            "noteType": 0,
            "laneNum": 2,
            "startTime": 98.4,
            "endTime": 98.4
        },
        {
            "noteType": 0,
            "laneNum": 1,
            "startTime": 98.55,
            "endTime": 98.55
        },
        {
            "noteType": 0,
            "laneNum": 2,
            "startTime": 98.7,
            "endTime": 98.7
        },
        {
            "noteType": 0,
            "laneNum": 1,
            "startTime": 98.85,
            "endTime": 98.85
        },
        {
            "noteType": 0,
            "laneNum": 0,
            "startTime": 99.15,
            "endTime": 99.15
        },
        {
            "noteType": 0,
            "laneNum": 1,
            "startTime": 99.3,
            "endTime": 99.3
        },
        {
            "noteType": 1,
            "laneNum": 0,
            "startTime": 99.6,
            "endTime": 100.2
        },
        {
            "noteType": 1,
            "laneNum": 2,
            "startTime": 99.6,
            "endTime": 100.2
        },
        {
            "noteType": 0,
            "laneNum": 3,
            "startTime": 99.6,
            "endTime": 99.6
        },
        {
            "noteType": 0,
            "laneNum": 3,
            "startTime": 99.9,
            "endTime": 99.9
        },
        {
            "noteType": 0,
            "laneNum": 1,
            "startTime": 100.2,
            "endTime": 100.2
        },
        {
            "noteType": 0,
            "laneNum": 3,
            "startTime": 100.5,
            "endTime": 100.5
        },
        {
            "noteType": 0,
            "laneNum": 2,
            "startTime": 100.8,
            "endTime": 100.8
        },
        {
            "noteType": 0,
            "laneNum": 1,
            "startTime": 100.95,
            "endTime": 100.95
        },
        {
            "noteType": 0,
            "laneNum": 2,
            "startTime": 101.1,
            "endTime": 101.1
        },
        {
            "noteType": 0,
            "laneNum": 1,
            "startTime": 101.25,
            "endTime": 101.25
        },
        {
            "noteType": 0,
            "laneNum": 3,
            "startTime": 101.55,
            "endTime": 101.55
        },
        {
            "noteType": 0,
            "laneNum": 2,
            "startTime": 101.7,
            "endTime": 101.7
        },
        {
            "noteType": 1,
            "laneNum": 0,
            "startTime": 102.0,
            "endTime": 102.6
        },
        {
            "noteType": 0,
            "laneNum": 1,
            "startTime": 102.0,
            "endTime": 102.0
        },
        {
            "noteType": 1,
            "laneNum": 2,
            "startTime": 102.0,
            "endTime": 102.6
        },
        {
            "noteType": 0,
            "laneNum": 3,
            "startTime": 102.3,
            "endTime": 102.3
        },
        {
            "noteType": 0,
            "laneNum": 1,
            "startTime": 102.6,
            "endTime": 102.6
        },
        {
            "noteType": 0,
            "laneNum": 2,
            "startTime": 102.9,
            "endTime": 102.9
        },
        {
            "noteType": 1,
            "laneNum": 0,
            "startTime": 103.2,
            "endTime": 103.8
        },
        {
            "noteType": 0,
            "laneNum": 1,
            "startTime": 103.2,
            "endTime": 103.2
        },
        {
            "noteType": 1,
            "laneNum": 3,
            "startTime": 103.2,
            "endTime": 103.8
        },
        {
            "noteType": 0,
            "laneNum": 2,
            "startTime": 103.35,
            "endTime": 103.35
        },
        {
            "noteType": 0,
            "laneNum": 1,
            "startTime": 103.5,
            "endTime": 103.5
        },
        {
            "noteType": 0,
            "laneNum": 2,
            "startTime": 103.65,
            "endTime": 103.65
        },
        {
            "noteType": 0,
            "laneNum": 1,
            "startTime": 103.95,
            "endTime": 103.95
        },
        {
            "noteType": 0,
            "laneNum": 2,
            "startTime": 104.1,
            "endTime": 104.1
        },
        {
            "noteType": 1,
            "laneNum": 0,
            "startTime": 104.4,
            "endTime": 105.0
        },
        {
            "noteType": 1,
            "laneNum": 1,
            "startTime": 104.4,
            "endTime": 105.0
        },
        {
            "noteType": 0,
            "laneNum": 2,
            "startTime": 104.7,
            "endTime": 104.7
        },
        {
            "noteType": 0,
            "laneNum": 2,
            "startTime": 105.0,
            "endTime": 105.0
        },
        {
            "noteType": 0,
            "laneNum": 3,
            "startTime": 105.0,
            "endTime": 105.0
        },
        {
            "noteType": 0,
            "laneNum": 2,
            "startTime": 105.3,
            "endTime": 105.3
        },
        {
            "noteType": 1,
            "laneNum": 0,
            "startTime": 105.6,
            "endTime": 106.2
        },
        {
            "noteType": 0,
            "laneNum": 1,
            "startTime": 105.6,
            "endTime": 105.6
        },
        {
            "noteType": 1,
            "laneNum": 3,
            "startTime": 105.6,
            "endTime": 106.2
        },
        {
            "noteType": 0,
            "laneNum": 2,
            "startTime": 105.75,
            "endTime": 105.75
        },
        {
            "noteType": 0,
            "laneNum": 1,
            "startTime": 105.9,
            "endTime": 105.9
        },
        {
            "noteType": 0,
            "laneNum": 2,
            "startTime": 106.05,
            "endTime": 106.05
        },
        {
            "noteType": 0,
            "laneNum": 1,
            "startTime": 106.35,
            "endTime": 106.35
        },
        {
            "noteType": 0,
            "laneNum": 2,
            "startTime": 106.5,
            "endTime": 106.5
        },
        {
            "noteType": 1,
            "laneNum": 1,
            "startTime": 106.8,
            "endTime": 107.4
        },
        {
            "noteType": 1,
            "laneNum": 3,
            "startTime": 106.8,
            "endTime": 107.4
        },
        {
            "noteType": 0,
            "laneNum": 2,
            "startTime": 107.1,
            "endTime": 107.1
        },
        {
            "noteType": 0,
            "laneNum": 0,
            "startTime": 107.4,
            "endTime": 107.4
        },
        {
            "noteType": 0,
            "laneNum": 1,
            "startTime": 107.7,
            "endTime": 107.7
        },
        {
            "noteType": 0,
            "laneNum": 0,
            "startTime": 108.0,
            "endTime": 108.0
        },
        {
            "noteType": 1,
            "laneNum": 1,
            "startTime": 108.0,
            "endTime": 108.6
        },
        {
            "noteType": 1,
            "laneNum": 2,
            "startTime": 108.0,
            "endTime": 108.6
        },
        {
            "noteType": 0,
            "laneNum": 3,
            "startTime": 108.15,
            "endTime": 108.15
        },
        {
            "noteType": 0,
            "laneNum": 0,
            "startTime": 108.3,
            "endTime": 108.3
        },
        {
            "noteType": 0,
            "laneNum": 3,
            "startTime": 108.45,
            "endTime": 108.45
        },
        {
            "noteType": 1,
            "laneNum": 0,
            "startTime": 109.2,
            "endTime": 109.8
        },
        {
            "noteType": 1,
            "laneNum": 2,
            "startTime": 109.2,
            "endTime": 109.8
        },
        {
            "noteType": 0,
            "laneNum": 3,
            "startTime": 109.5,
            "endTime": 109.5
        },
        {
            "noteType": 0,
            "laneNum": 1,
            "startTime": 109.8,
            "endTime": 109.8
        },
        {
            "noteType": 0,
            "laneNum": 0,
            "startTime": 110.1,
            "endTime": 110.1
        },
        {
            "noteType": 1,
            "laneNum": 1,
            "startTime": 110.4,
            "endTime": 111.0
        },
        {
            "noteType": 1,
            "laneNum": 2,
            "startTime": 110.4,
            "endTime": 111.0
        },
        {
            "noteType": 0,
            "laneNum": 3,
            "startTime": 110.4,
            "endTime": 110.4
        },
        {
            "noteType": 0,
            "laneNum": 0,
            "startTime": 110.55,
            "endTime": 110.55
        },
        {
            "noteType": 0,
            "laneNum": 3,
            "startTime": 110.7,
            "endTime": 110.7
        },
        {
            "noteType": 0,
            "laneNum": 0,
            "startTime": 110.85,
            "endTime": 110.85
        },
        {
            "noteType": 1,
            "laneNum": 0,
            "startTime": 111.6,
            "endTime": 112.2
        },
        {
            "noteType": 1,
            "laneNum": 1,
            "startTime": 111.6,
            "endTime": 112.2
        },
        {
            "noteType": 0,
            "laneNum": 3,
            "startTime": 111.9,
            "endTime": 111.9
        },
        {
            "noteType": 0,
            "laneNum": 2,
            "startTime": 112.2,
            "endTime": 112.2
        },
        {
            "noteType": 0,
            "laneNum": 0,
            "startTime": 112.5,
            "endTime": 112.5
        },
        {
            "noteType": 0,
            "laneNum": 2,
            "startTime": 112.8,
            "endTime": 112.8
        },
        {
            "noteType": 1,
            "laneNum": 3,
            "startTime": 112.8,
            "endTime": 117.6
        },
        {
            "noteType": 0,
            "laneNum": 0,
            "startTime": 113.1,
            "endTime": 113.1
        },
        {
            "noteType": 0,
            "laneNum": 1,
            "startTime": 113.25,
            "endTime": 113.25
        },
        {
            "noteType": 1,
            "laneNum": 1,
            "startTime": 114.0,
            "endTime": 114.6
        },
        {
            "noteType": 0,
            "laneNum": 2,
            "startTime": 114.0,
            "endTime": 114.0
        },
        {
            "noteType": 0,
            "laneNum": 0,
            "startTime": 114.3,
            "endTime": 114.3
        },
        {
            "noteType": 0,
            "laneNum": 2,
            "startTime": 114.6,
            "endTime": 114.6
        },
        {
            "noteType": 0,
            "laneNum": 0,
            "startTime": 114.9,
            "endTime": 114.9
        },
        {
            "noteType": 0,
            "laneNum": 1,
            "startTime": 115.2,
            "endTime": 115.2
        },
        {
            "noteType": 0,
            "laneNum": 2,
            "startTime": 115.5,
            "endTime": 115.5
        },
        {
            "noteType": 0,
            "laneNum": 0,
            "startTime": 115.65,
            "endTime": 115.65
        },
        {
            "noteType": 0,
            "laneNum": 1,
            "startTime": 116.4,
            "endTime": 116.4
        },
        {
            "noteType": 1,
            "laneNum": 2,
            "startTime": 116.4,
            "endTime": 117.0
        },
        {
            "noteType": 0,
            "laneNum": 0,
            "startTime": 116.7,
            "endTime": 116.7
        },
        {
            "noteType": 0,
            "laneNum": 1,
            "startTime": 117.0,
            "endTime": 117.0
        },
        {
            "noteType": 0,
            "laneNum": 0,
            "startTime": 117.3,
            "endTime": 117.3
        },
        {
            "noteType": 1,
            "laneNum": 0,
            "startTime": 117.9,
            "endTime": 118.2
        },
        {
            "noteType": 0,
            "laneNum": 1,
            "startTime": 118.05,
            "endTime": 118.05
        },
        {
            "noteType": 0,
            "laneNum": 3,
            "startTime": 118.35,
            "endTime": 118.35
        },
        {
            "noteType": 1,
            "laneNum": 1,
            "startTime": 118.5,
            "endTime": 118.8
        },
        {
            "noteType": 0,
            "laneNum": 2,
            "startTime": 118.5,
            "endTime": 118.5
        },
        {
            "noteType": 0,
            "laneNum": 0,
            "startTime": 118.8,
            "endTime": 118.8
        },
        {
            "noteType": 1,
            "laneNum": 3,
            "startTime": 119.1,
            "endTime": 119.4
        },
        {
            "noteType": 0,
            "laneNum": 2,
            "startTime": 119.25,
            "endTime": 119.25
        },
        {
            "noteType": 0,
            "laneNum": 0,
            "startTime": 119.55,
            "endTime": 119.55
        },
        {
            "noteType": 0,
            "laneNum": 2,
            "startTime": 119.7,
            "endTime": 119.7
        },
        {
            "noteType": 1,
            "laneNum": 3,
            "startTime": 119.7,
            "endTime": 120.0
        },
        {
            "noteType": 0,
            "laneNum": 1,
            "startTime": 119.85,
            "endTime": 119.85
        },
        {
            "noteType": 0,
            "laneNum": 2,
            "startTime": 120.0,
            "endTime": 120.0
        },
        {
            "noteType": 1,
            "laneNum": 1,
            "startTime": 120.3,
            "endTime": 120.6
        },
        {
            "noteType": 0,
            "laneNum": 0,
            "startTime": 120.45,
            "endTime": 120.45
        },
        {
            "noteType": 0,
            "laneNum": 2,
            "startTime": 120.75,
            "endTime": 120.75
        },
        {
            "noteType": 1,
            "laneNum": 0,
            "startTime": 120.9,
            "endTime": 121.2
        },
        {
            "noteType": 0,
            "laneNum": 3,
            "startTime": 120.9,
            "endTime": 120.9
        },
        {
            "noteType": 0,
            "laneNum": 1,
            "startTime": 121.2,
            "endTime": 121.2
        },
        {
            "noteType": 1,
            "laneNum": 2,
            "startTime": 121.5,
            "endTime": 121.8
        },
        {
            "noteType": 0,
            "laneNum": 0,
            "startTime": 121.65,
            "endTime": 121.65
        },
        {
            "noteType": 0,
            "laneNum": 3,
            "startTime": 121.95,
            "endTime": 121.95
        },
        {
            "noteType": 1,
            "laneNum": 1,
            "startTime": 122.1,
            "endTime": 122.4
        },
        {
            "noteType": 0,
            "laneNum": 2,
            "startTime": 122.1,
            "endTime": 122.1
        },
        {
            "noteType": 0,
            "laneNum": 0,
            "startTime": 122.4,
            "endTime": 122.4
        },
        {
            "noteType": 1,
            "laneNum": 2,
            "startTime": 122.7,
            "endTime": 123.0
        },
        {
            "noteType": 0,
            "laneNum": 1,
            "startTime": 122.85,
            "endTime": 122.85
        },
        {
            "noteType": 0,
            "laneNum": 3,
            "startTime": 123.15,
            "endTime": 123.15
        },
        {
            "noteType": 1,
            "laneNum": 1,
            "startTime": 123.3,
            "endTime": 123.6
        },
        {
            "noteType": 0,
            "laneNum": 2,
            "startTime": 123.3,
            "endTime": 123.3
        },
        {
            "noteType": 0,
            "laneNum": 0,
            "startTime": 123.6,
            "endTime": 123.6
        },
        {
            "noteType": 1,
            "laneNum": 0,
            "startTime": 123.9,
            "endTime": 124.2
        },
        {
            "noteType": 0,
            "laneNum": 3,
            "startTime": 124.05,
            "endTime": 124.05
        },
        {
            "noteType": 0,
            "laneNum": 3,
            "startTime": 124.35,
            "endTime": 124.35
        },
        {
            "noteType": 1,
            "laneNum": 1,
            "startTime": 124.5,
            "endTime": 124.8
        },
        {
            "noteType": 0,
            "laneNum": 2,
            "startTime": 124.5,
            "endTime": 124.5
        },
        {
            "noteType": 0,
            "laneNum": 3,
            "startTime": 124.65,
            "endTime": 124.65
        },
        {
            "noteType": 0,
            "laneNum": 0,
            "startTime": 124.8,
            "endTime": 124.8
        },
        {
            "noteType": 1,
            "laneNum": 3,
            "startTime": 125.1,
            "endTime": 125.4
        },
        {
            "noteType": 0,
            "laneNum": 2,
            "startTime": 125.25,
            "endTime": 125.25
        },
        {
            "noteType": 0,
            "laneNum": 0,
            "startTime": 125.55,
            "endTime": 125.55
        },
        {
            "noteType": 0,
            "laneNum": 1,
            "startTime": 125.7,
            "endTime": 125.7
        },
        {
            "noteType": 1,
            "laneNum": 2,
            "startTime": 125.7,
            "endTime": 126.0
        },
        {
            "noteType": 0,
            "laneNum": 3,
            "startTime": 126.0,
            "endTime": 126.0
        },
        {
            "noteType": 1,
            "laneNum": 1,
            "startTime": 126.3,
            "endTime": 126.6
        },
        {
            "noteType": 0,
            "laneNum": 2,
            "startTime": 126.45,
            "endTime": 126.45
        },
        {
            "noteType": 0,
            "laneNum": 0,
            "startTime": 126.75,
            "endTime": 126.75
        },
        {
            "noteType": 0,
            "laneNum": 1,
            "startTime": 126.9,
            "endTime": 126.9
        },
        {
            "noteType": 1,
            "laneNum": 0,
            "startTime": 127.2,
            "endTime": 129.6
        },
        {
            "noteType": 1,
            "laneNum": 3,
            "startTime": 127.2,
            "endTime": 130.2
        },
        {
            "noteType": 1,
            "laneNum": 1,
            "startTime": 127.5,
            "endTime": 128.7
        },
        {
            "noteType": 1,
            "laneNum": 2,
            "startTime": 128.1,
            "endTime": 129.3
        }
    ]
}