{
    "guid": "8c30f4a2-5dd5-430d-a348-7737b72980ed",
    "id": 1000077,
    "title": "Stonedrider_Shredderz_186bpm.wav",
    "createdAt": 1700039578,
    "updatedAt": 1700120335,
    "bpm": 186,
    "signature": 4,
    "fileName": "",
    "difficulty": 1,
    "noteList": [
        {
            "noteType": 1,
            "laneNum": 0,
            "startTime": 2.5806,
            "endTime": 3.0645
        },
        {
            "noteType": 1,
            "laneNum": 2,
            "startTime": 3.5484,
            "endTime": 3.7097
        },
        {
            "noteType": 1,
            "laneNum": 1,
            "startTime": 3.871,
            "endTime": 4.3548
        },
        {
            "noteType": 1,
            "laneNum": 3,
            "startTime": 4.8387,
            "endTime": 5.0
        },
        {
            "noteType": 1,
            "laneNum": 2,
            "startTime": 5.1613,
            "endTime": 5.6452
        },
        {
            "noteType": 1,
            "laneNum": 0,
            "startTime": 6.129,
            "endTime": 6.2903
        },
        {
            "noteType": 1,
            "laneNum": 3,
            "startTime": 6.4516,
            "endTime": 6.9355
        },
        {
            "noteType": 1,
            "laneNum": 1,
            "startTime": 7.4194,
            "endTime": 7.5806
        },
        {
            "noteType": 1,
            "laneNum": 0,
            "startTime": 7.7419,
            "endTime": 8.2258
        },
        {
            "noteType": 1,
            "laneNum": 2,
            "startTime": 8.7097,
            "endTime": 8.871
        },
        {
            "noteType": 1,
            "laneNum": 1,
            "startTime": 9.0323,
            "endTime": 9.5161
        },
        {
            "noteType": 1,
            "laneNum": 0,
            "startTime": 10.0,
            "endTime": 10.1613
        },
        {
            "noteType": 1,
            "laneNum": 2,
            "startTime": 10.3226,
            "endTime": 10.8065
        },
        {
            "noteType": 1,
            "laneNum": 1,
            "startTime": 11.2903,
            "endTime": 11.4516
        },
        {
            "noteType": 1,
            "laneNum": 0,
            "startTime": 11.6129,
            "endTime": 12.2581
        },
        {
            "noteType": 1,
            "laneNum": 3,
            "startTime": 12.2581,
            "endTime": 12.9032
        },
        {
            "noteType": 1,
            "laneNum": 2,
            "startTime": 12.9032,
            "endTime": 13.2258
        },
        {
            "noteType": 0,
            "laneNum": 0,
            "startTime": 13.2258,
            "endTime": 13.2258
        },
        {
            "noteType": 0,
            "laneNum": 1,
            "startTime": 13.5484,
            "endTime": 13.5484
        },
        {
            "noteType": 0,
            "laneNum": 2,
            "startTime": 13.7097,
            "endTime": 13.7097
        },
        {
            "noteType": 0,
            "laneNum": 1,
            "startTime": 13.871,
            "endTime": 13.871
        },
        {
            "noteType": 1,
            "laneNum": 3,
            "startTime": 14.0323,
            "endTime": 15.6452
        },
        {
            "noteType": 0,
            "laneNum": 0,
            "startTime": 15.6452,
            "endTime": 15.6452
        },
        {
            "noteType": 0,
            "laneNum": 3,
            "startTime": 15.8065,
            "endTime": 15.8065
        },
        {
            "noteType": 0,
            "laneNum": 2,
            "startTime": 15.9677,
            "endTime": 15.9677
        },
        {
            "noteType": 0,
            "laneNum": 1,
            "startTime": 16.129,
            "endTime": 16.129
        },
        {
            "noteType": 0,
            "laneNum": 0,
            "startTime": 16.2903,
            "endTime": 16.2903
        },
        {
            "noteType": 0,
            "laneNum": 3,
            "startTime": 16.4516,
            "endTime": 16.4516
        },
        {
            "noteType": 1,
            "laneNum": 1,
            "startTime": 16.6129,
            "endTime": 18.0645
        },
        {
            "noteType": 0,
            "laneNum": 2,
            "startTime": 18.0645,
            "endTime": 18.0645
        },
        {
            "noteType": 0,
            "laneNum": 3,
            "startTime": 18.5484,
            "endTime": 18.5484
        },
        {
            "noteType": 0,
            "laneNum": 1,
            "startTime": 18.7097,
            "endTime": 18.7097
        },
        {
            "noteType": 0,
            "laneNum": 0,
            "startTime": 18.871,
            "endTime": 18.871
        },
        {
            "noteType": 0,
            "laneNum": 2,
            "startTime": 19.0323,
            "endTime": 19.0323
        },
        {
            "noteType": 1,
            "laneNum": 1,
            "startTime": 19.1935,
            "endTime": 19.6774
        },
        {
            "noteType": 0,
            "laneNum": 3,
            "startTime": 19.6774,
            "endTime": 19.6774
        },
        {
            "noteType": 0,
            "laneNum": 2,
            "startTime": 19.7581,
            "endTime": 19.7581
        },
        {
            "noteType": 0,
            "laneNum": 0,
            "startTime": 19.8387,
            "endTime": 19.8387
        },
        {
            "noteType": 0,
            "laneNum": 3,
            "startTime": 20.0,
            "endTime": 20.0
        },
        {
            "noteType": 1,
            "laneNum": 2,
            "startTime": 20.1613,
            "endTime": 20.6452
        },
        {
            "noteType": 0,
            "laneNum": 3,
            "startTime": 21.2903,
            "endTime": 21.2903
        },
        {
            "noteType": 0,
            "laneNum": 2,
            "startTime": 21.4516,
            "endTime": 21.4516
        },
        {
            "noteType": 0,
            "laneNum": 0,
            "startTime": 21.7742,
            "endTime": 21.7742
        },
        {
            "noteType": 0,
            "laneNum": 0,
            "startTime": 22.2581,
            "endTime": 22.2581
        },
        {
            "noteType": 0,
            "laneNum": 1,
            "startTime": 22.4194,
            "endTime": 22.4194
        },
        {
            "noteType": 0,
            "laneNum": 0,
            "startTime": 22.5806,
            "endTime": 22.5806
        },
        {
            "noteType": 0,
            "laneNum": 1,
            "startTime": 22.7419,
            "endTime": 22.7419
        },
        {
            "noteType": 0,
            "laneNum": 0,
            "startTime": 22.9032,
            "endTime": 22.9032
        },
        {
            "noteType": 0,
            "laneNum": 1,
            "startTime": 23.0645,
            "endTime": 23.0645
        },
        {
            "noteType": 0,
            "laneNum": 3,
            "startTime": 23.2258,
            "endTime": 23.2258
        },
        {
            "noteType": 0,
            "laneNum": 1,
            "startTime": 23.5484,
            "endTime": 23.5484
        },
        {
            "noteType": 0,
            "laneNum": 3,
            "startTime": 23.871,
            "endTime": 23.871
        },
        {
            "noteType": 0,
            "laneNum": 3,
            "startTime": 24.0323,
            "endTime": 24.0323
        },
        {
            "noteType": 0,
            "laneNum": 1,
            "startTime": 24.1936,
            "endTime": 24.1936
        },
        {
            "noteType": 0,
            "laneNum": 2,
            "startTime": 24.5161,
            "endTime": 24.5161
        },
        {
            "noteType": 0,
            "laneNum": 0,
            "startTime": 24.8387,
            "endTime": 24.8387
        },
        {
            "noteType": 0,
            "laneNum": 2,
            "startTime": 25.1613,
            "endTime": 25.1613
        },
        {
            "noteType": 0,
            "laneNum": 2,
            "startTime": 25.3226,
            "endTime": 25.3226
        },
        {
            "noteType": 0,
            "laneNum": 0,
            "startTime": 25.4839,
            "endTime": 25.4839
        },
        {
            "noteType": 0,
            "laneNum": 1,
            "startTime": 25.8065,
            "endTime": 25.8065
        },
        {
            "noteType": 0,
            "laneNum": 2,
            "startTime": 26.129,
            "endTime": 26.129
        },
        {
            "noteType": 0,
            "laneNum": 1,
            "startTime": 26.4516,
            "endTime": 26.4516
        },
        {
            "noteType": 0,
            "laneNum": 2,
            "startTime": 26.4516,
            "endTime": 26.4516
        },
        {
            "noteType": 0,
            "laneNum": 1,
            "startTime": 26.7742,
            "endTime": 26.7742
        },
        {
            "noteType": 0,
            "laneNum": 2,
            "startTime": 26.7742,
            "endTime": 26.7742
        },
        {
            "noteType": 0,
            "laneNum": 3,
            "startTime": 27.0968,
            "endTime": 27.0968
        },
        {
            "noteType": 0,
            "laneNum": 2,
            "startTime": 27.2581,
            "endTime": 27.2581
        },
        {
            "noteType": 0,
            "laneNum": 1,
            "startTime": 27.4194,
            "endTime": 27.4194
        },
        {
            "noteType": 0,
            "laneNum": 0,
            "startTime": 27.5806,
            "endTime": 27.5806
        },
        {
            "noteType": 0,
            "laneNum": 0,
            "startTime": 27.9032,
            "endTime": 27.9032
        },
        {
            "noteType": 0,
            "laneNum": 0,
            "startTime": 28.2258,
            "endTime": 28.2258
        },
        {
            "noteType": 1,
            "laneNum": 3,
            "startTime": 28.3871,
            "endTime": 29.6774
        },
        {
            "noteType": 0,
            "laneNum": 2,
            "startTime": 28.7097,
            "endTime": 28.7097
        },
        {
            "noteType": 0,
            "laneNum": 2,
            "startTime": 29.3548,
            "endTime": 29.3548
        },
        {
            "noteType": 1,
            "laneNum": 2,
            "startTime": 29.6774,
            "endTime": 30.9677
        },
        {
            "noteType": 0,
            "laneNum": 1,
            "startTime": 30.0,
            "endTime": 30.0
        },
        {
            "noteType": 0,
            "laneNum": 1,
            "startTime": 30.6452,
            "endTime": 30.6452
        },
        {
            "noteType": 1,
            "laneNum": 1,
            "startTime": 30.9677,
            "endTime": 32.2581
        },
        {
            "noteType": 0,
            "laneNum": 3,
            "startTime": 31.2903,
            "endTime": 31.2903
        },
        {
            "noteType": 0,
            "laneNum": 3,
            "startTime": 31.9355,
            "endTime": 31.9355
        },
        {
            "noteType": 0,
            "laneNum": 0,
            "startTime": 32.5806,
            "endTime": 32.5806
        },
        {
            "noteType": 0,
            "laneNum": 0,
            "startTime": 33.2258,
            "endTime": 33.2258
        },
        {
            "noteType": 1,
            "laneNum": 2,
            "startTime": 33.2258,
            "endTime": 33.5484
        },
        {
            "noteType": 0,
            "laneNum": 3,
            "startTime": 33.7097,
            "endTime": 33.7097
        },
        {
            "noteType": 0,
            "laneNum": 2,
            "startTime": 33.871,
            "endTime": 33.871
        },
        {
            "noteType": 0,
            "laneNum": 1,
            "startTime": 34.0323,
            "endTime": 34.0323
        },
        {
            "noteType": 0,
            "laneNum": 3,
            "startTime": 34.1935,
            "endTime": 34.1935
        },
        {
            "noteType": 0,
            "laneNum": 0,
            "startTime": 34.3548,
            "endTime": 34.3548
        },
        {
            "noteType": 0,
            "laneNum": 1,
            "startTime": 34.5161,
            "endTime": 34.5161
        },
        {
            "noteType": 0,
            "laneNum": 2,
            "startTime": 34.6774,
            "endTime": 34.6774
        },
        {
            "noteType": 0,
            "laneNum": 0,
            "startTime": 34.8387,
            "endTime": 34.8387
        },
        {
            "noteType": 0,
            "laneNum": 3,
            "startTime": 35.0,
            "endTime": 35.0
        },
        {
            "noteType": 0,
            "laneNum": 1,
            "startTime": 35.1613,
            "endTime": 35.1613
        },
        {
            "noteType": 0,
            "laneNum": 2,
            "startTime": 35.3226,
            "endTime": 35.3226
        },
        {
            "noteType": 0,
            "laneNum": 0,
            "startTime": 35.4839,
            "endTime": 35.4839
        },
        {
            "noteType": 0,
            "laneNum": 3,
            "startTime": 35.6452,
            "endTime": 35.6452
        },
        {
            "noteType": 0,
            "laneNum": 1,
            "startTime": 35.8065,
            "endTime": 35.8065
        },
        {
            "noteType": 0,
            "laneNum": 0,
            "startTime": 35.9677,
            "endTime": 35.9677
        },
        {
            "noteType": 0,
            "laneNum": 3,
            "startTime": 36.129,
            "endTime": 36.129
        },
        {
            "noteType": 0,
            "laneNum": 2,
            "startTime": 36.2903,
            "endTime": 36.2903
        },
        {
            "noteType": 1,
            "laneNum": 1,
            "startTime": 36.4516,
            "endTime": 36.6129
        },
        {
            "noteType": 0,
            "laneNum": 3,
            "startTime": 36.7742,
            "endTime": 36.7742
        },
        {
            "noteType": 0,
            "laneNum": 1,
            "startTime": 37.0968,
            "endTime": 37.0968
        },
        {
            "noteType": 0,
            "laneNum": 1,
            "startTime": 37.2581,
            "endTime": 37.2581
        },
        {
            "noteType": 0,
            "laneNum": 3,
            "startTime": 37.4194,
            "endTime": 37.4194
        },
        {
            "noteType": 0,
            "laneNum": 2,
            "startTime": 37.5806,
            "endTime": 37.5806
        },
        {
            "noteType": 0,
            "laneNum": 3,
            "startTime": 37.7419,
            "endTime": 37.7419
        },
        {
            "noteType": 0,
            "laneNum": 2,
            "startTime": 37.9032,
            "endTime": 37.9032
        },
        {
            "noteType": 0,
            "laneNum": 0,
            "startTime": 38.0645,
            "endTime": 38.0645
        },
        {
            "noteType": 0,
            "laneNum": 1,
            "startTime": 38.2258,
            "endTime": 38.2258
        },
        {
            "noteType": 0,
            "laneNum": 0,
            "startTime": 38.3871,
            "endTime": 38.3871
        },
        {
            "noteType": 0,
            "laneNum": 1,
            "startTime": 38.5484,
            "endTime": 38.5484
        },
        {
            "noteType": 1,
            "laneNum": 2,
            "startTime": 38.7097,
            "endTime": 39.3548
        },
        {
            "noteType": 0,
            "laneNum": 0,
            "startTime": 39.3548,
            "endTime": 39.3548
        },
        {
            "noteType": 0,
            "laneNum": 2,
            "startTime": 39.6774,
            "endTime": 39.6774
        },
        {
            "noteType": 1,
            "laneNum": 1,
            "startTime": 39.8387,
            "endTime": 40.4839
        },
        {
            "noteType": 0,
            "laneNum": 3,
            "startTime": 40.6452,
            "endTime": 40.6452
        },
        {
            "noteType": 0,
            "laneNum": 2,
            "startTime": 40.8065,
            "endTime": 40.8065
        },
        {
            "noteType": 1,
            "laneNum": 1,
            "startTime": 40.9677,
            "endTime": 41.6129
        },
        {
            "noteType": 0,
            "laneNum": 0,
            "startTime": 41.6129,
            "endTime": 41.6129
        },
        {
            "noteType": 0,
            "laneNum": 2,
            "startTime": 41.7742,
            "endTime": 41.7742
        },
        {
            "noteType": 0,
            "laneNum": 3,
            "startTime": 41.9355,
            "endTime": 41.9355
        },
        {
            "noteType": 1,
            "laneNum": 2,
            "startTime": 42.0968,
            "endTime": 42.2581
        },
        {
            "noteType": 1,
            "laneNum": 1,
            "startTime": 42.4194,
            "endTime": 42.9032
        },
        {
            "noteType": 1,
            "laneNum": 0,
            "startTime": 43.2258,
            "endTime": 43.871
        },
        {
            "noteType": 1,
            "laneNum": 1,
            "startTime": 43.871,
            "endTime": 45.1613
        },
        {
            "noteType": 1,
            "laneNum": 2,
            "startTime": 45.1613,
            "endTime": 46.4516
        },
        {
            "noteType": 1,
            "laneNum": 0,
            "startTime": 46.4516,
            "endTime": 47.7419
        },
        {
            "noteType": 1,
            "laneNum": 2,
            "startTime": 47.7419,
            "endTime": 49.0323
        },
        {
            "noteType": 0,
            "laneNum": 3,
            "startTime": 48.0645,
            "endTime": 48.0645
        },
        {
            "noteType": 0,
            "laneNum": 3,
            "startTime": 48.2258,
            "endTime": 48.2258
        },
        {
            "noteType": 0,
            "laneNum": 1,
            "startTime": 48.3871,
            "endTime": 48.3871
        },
        {
            "noteType": 0,
            "laneNum": 1,
            "startTime": 48.5484,
            "endTime": 48.5484
        },
        {
            "noteType": 0,
            "laneNum": 3,
            "startTime": 48.7097,
            "endTime": 48.7097
        },
        {
            "noteType": 0,
            "laneNum": 3,
            "startTime": 48.871,
            "endTime": 48.871
        },
        {
            "noteType": 1,
            "laneNum": 1,
            "startTime": 49.0323,
            "endTime": 49.6774
        },
        {
            "noteType": 0,
            "laneNum": 0,
            "startTime": 49.6774,
            "endTime": 49.6774
        },
        {
            "noteType": 0,
            "laneNum": 3,
            "startTime": 50.0,
            "endTime": 50.0
        },
        {
            "noteType": 1,
            "laneNum": 1,
            "startTime": 50.1613,
            "endTime": 50.4839
        },
        {
            "noteType": 1,
            "laneNum": 2,
            "startTime": 50.6452,
            "endTime": 50.8065
        },
        {
            "noteType": 1,
            "laneNum": 3,
            "startTime": 50.9677,
            "endTime": 51.129
        },
        {
            "noteType": 1,
            "laneNum": 1,
            "startTime": 51.129,
            "endTime": 51.2903
        },
        {
            "noteType": 1,
            "laneNum": 0,
            "startTime": 51.2903,
            "endTime": 51.4516
        },
        {
            "noteType": 1,
            "laneNum": 2,
            "startTime": 51.4516,
            "endTime": 51.9355
        },
        {
            "noteType": 1,
            "laneNum": 1,
            "startTime": 51.9355,
            "endTime": 52.0968
        },
        {
            "noteType": 1,
            "laneNum": 3,
            "startTime": 52.2581,
            "endTime": 52.4194
        },
        {
            "noteType": 1,
            "laneNum": 2,
            "startTime": 52.4194,
            "endTime": 52.7419
        },
        {
            "noteType": 1,
            "laneNum": 0,
            "startTime": 52.7419,
            "endTime": 54.1936
        },
        {
            "noteType": 1,
            "laneNum": 2,
            "startTime": 54.1936,
            "endTime": 55.4839
        },
        {
            "noteType": 1,
            "laneNum": 0,
            "startTime": 55.4839,
            "endTime": 55.6452
        },
        {
            "noteType": 1,
            "laneNum": 3,
            "startTime": 55.8065,
            "endTime": 55.9677
        },
        {
            "noteType": 1,
            "laneNum": 2,
            "startTime": 56.129,
            "endTime": 56.2903
        },
        {
            "noteType": 1,
            "laneNum": 1,
            "startTime": 56.2903,
            "endTime": 56.4516
        },
        {
            "noteType": 1,
            "laneNum": 0,
            "startTime": 56.4516,
            "endTime": 56.7742
        },
        {
            "noteType": 0,
            "laneNum": 1,
            "startTime": 57.0968,
            "endTime": 57.0968
        },
        {
            "noteType": 0,
            "laneNum": 1,
            "startTime": 57.4194,
            "endTime": 57.4194
        },
        {
            "noteType": 0,
            "laneNum": 1,
            "startTime": 57.7419,
            "endTime": 57.7419
        },
        {
            "noteType": 1,
            "laneNum": 0,
            "startTime": 58.0645,
            "endTime": 59.3548
        },
        {
            "noteType": 0,
            "laneNum": 2,
            "startTime": 58.0645,
            "endTime": 58.0645
        },
        {
            "noteType": 0,
            "laneNum": 1,
            "startTime": 58.3871,
            "endTime": 58.3871
        },
        {
            "noteType": 0,
            "laneNum": 1,
            "startTime": 58.5484,
            "endTime": 58.5484
        },
        {
            "noteType": 0,
            "laneNum": 2,
            "startTime": 58.7097,
            "endTime": 58.7097
        },
        {
            "noteType": 0,
            "laneNum": 2,
            "startTime": 58.871,
            "endTime": 58.871
        },
        {
            "noteType": 0,
            "laneNum": 3,
            "startTime": 59.0323,
            "endTime": 59.0323
        },
        {
            "noteType": 0,
            "laneNum": 3,
            "startTime": 59.1935,
            "endTime": 59.1935
        },
        {
            "noteType": 1,
            "laneNum": 2,
            "startTime": 59.3548,
            "endTime": 60.0
        },
        {
            "noteType": 0,
            "laneNum": 0,
            "startTime": 60.0,
            "endTime": 60.0
        },
        {
            "noteType": 0,
            "laneNum": 1,
            "startTime": 60.1613,
            "endTime": 60.1613
        },
        {
            "noteType": 0,
            "laneNum": 2,
            "startTime": 60.3226,
            "endTime": 60.3226
        },
        {
            "noteType": 0,
            "laneNum": 3,
            "startTime": 60.4839,
            "endTime": 60.4839
        },
        {
            "noteType": 1,
            "laneNum": 2,
            "startTime": 60.6452,
            "endTime": 61.9355
        },
        {
            "noteType": 0,
            "laneNum": 3,
            "startTime": 61.9355,
            "endTime": 61.9355
        },
        {
            "noteType": 0,
            "laneNum": 3,
            "startTime": 62.2581,
            "endTime": 62.2581
        },
        {
            "noteType": 0,
            "laneNum": 3,
            "startTime": 62.5806,
            "endTime": 62.5806
        },
        {
            "noteType": 0,
            "laneNum": 2,
            "startTime": 62.7419,
            "endTime": 62.7419
        },
        {
            "noteType": 0,
            "laneNum": 0,
            "startTime": 62.9032,
            "endTime": 62.9032
        },
        {
            "noteType": 1,
            "laneNum": 1,
            "startTime": 63.0645,
            "endTime": 64.5161
        },
        {
            "noteType": 1,
            "laneNum": 2,
            "startTime": 64.5161,
            "endTime": 65.1613
        },
        {
            "noteType": 0,
            "laneNum": 3,
            "startTime": 65.1613,
            "endTime": 65.1613
        },
        {
            "noteType": 0,
            "laneNum": 2,
            "startTime": 65.3763,
            "endTime": 65.3763
        },
        {
            "noteType": 0,
            "laneNum": 1,
            "startTime": 65.5914,
            "endTime": 65.5914
        },
        {
            "noteType": 0,
            "laneNum": 0,
            "startTime": 65.8065,
            "endTime": 65.8065
        },
        {
            "noteType": 1,
            "laneNum": 2,
            "startTime": 65.9677,
            "endTime": 67.2581
        },
        {
            "noteType": 0,
            "laneNum": 3,
            "startTime": 67.2581,
            "endTime": 67.2581
        },
        {
            "noteType": 0,
            "laneNum": 2,
            "startTime": 67.4194,
            "endTime": 67.4194
        },
        {
            "noteType": 0,
            "laneNum": 0,
            "startTime": 67.5806,
            "endTime": 67.5806
        },
        {
            "noteType": 1,
            "laneNum": 1,
            "startTime": 67.7419,
            "endTime": 68.3871
        },
        {
            "noteType": 0,
            "laneNum": 2,
            "startTime": 68.3871,
            "endTime": 68.3871
        },
        {
            "noteType": 1,
            "laneNum": 0,
            "startTime": 68.7097,
            "endTime": 69.5161
        },
        {
            "noteType": 0,
            "laneNum": 3,
            "startTime": 69.6774,
            "endTime": 69.6774
        },
        {
            "noteType": 0,
            "laneNum": 2,
            "startTime": 69.7581,
            "endTime": 69.7581
        },
        {
            "noteType": 0,
            "laneNum": 1,
            "startTime": 69.8387,
            "endTime": 69.8387
        },
        {
            "noteType": 0,
            "laneNum": 0,
            "startTime": 69.9194,
            "endTime": 69.9194
        },
        {
            "noteType": 0,
            "laneNum": 3,
            "startTime": 70.0,
            "endTime": 70.0
        },
        {
            "noteType": 0,
            "laneNum": 2,
            "startTime": 70.0806,
            "endTime": 70.0806
        },
        {
            "noteType": 0,
            "laneNum": 1,
            "startTime": 70.1613,
            "endTime": 70.1613
        },
        {
            "noteType": 0,
            "laneNum": 0,
            "startTime": 70.2419,
            "endTime": 70.2419
        },
        {
            "noteType": 0,
            "laneNum": 2,
            "startTime": 70.3226,
            "endTime": 70.3226
        },
        {
            "noteType": 0,
            "laneNum": 1,
            "startTime": 70.4032,
            "endTime": 70.4032
        },
        {
            "noteType": 0,
            "laneNum": 3,
            "startTime": 70.4839,
            "endTime": 70.4839
        },
        {
            "noteType": 0,
            "laneNum": 2,
            "startTime": 70.5645,
            "endTime": 70.5645
        },
        {
            "noteType": 0,
            "laneNum": 0,
            "startTime": 70.6452,
            "endTime": 70.6452
        },
        {
            "noteType": 0,
            "laneNum": 1,
            "startTime": 70.7258,
            "endTime": 70.7258
        },
        {
            "noteType": 0,
            "laneNum": 3,
            "startTime": 70.8065,
            "endTime": 70.8065
        },
        {
            "noteType": 0,
            "laneNum": 2,
            "startTime": 70.8871,
            "endTime": 70.8871
        },
        {
            "noteType": 0,
            "laneNum": 1,
            "startTime": 70.9677,
            "endTime": 70.9677
        },
        {
            "noteType": 0,
            "laneNum": 0,
            "startTime": 71.0484,
            "endTime": 71.0484
        },
        {
            "noteType": 0,
            "laneNum": 2,
            "startTime": 71.129,
            "endTime": 71.129
        },
        {
            "noteType": 0,
            "laneNum": 1,
            "startTime": 71.2097,
            "endTime": 71.2097
        },
        {
            "noteType": 0,
            "laneNum": 0,
            "startTime": 71.2903,
            "endTime": 71.2903
        },
        {
            "noteType": 0,
            "laneNum": 3,
            "startTime": 71.371,
            "endTime": 71.371
        },
        {
            "noteType": 0,
            "laneNum": 1,
            "startTime": 71.4516,
            "endTime": 71.4516
        },
        {
            "noteType": 0,
            "laneNum": 2,
            "startTime": 71.5323,
            "endTime": 71.5323
        },
        {
            "noteType": 0,
            "laneNum": 0,
            "startTime": 71.6129,
            "endTime": 71.6129
        },
        {
            "noteType": 0,
            "laneNum": 1,
            "startTime": 71.6935,
            "endTime": 71.6935
        },
        {
            "noteType": 0,
            "laneNum": 3,
            "startTime": 71.7742,
            "endTime": 71.7742
        },
        {
            "noteType": 0,
            "laneNum": 2,
            "startTime": 71.8548,
            "endTime": 71.8548
        },
        {
            "noteType": 0,
            "laneNum": 1,
            "startTime": 71.9355,
            "endTime": 71.9355
        },
        {
            "noteType": 0,
            "laneNum": 0,
            "startTime": 72.0161,
            "endTime": 72.0161
        },
        {
            "noteType": 0,
            "laneNum": 2,
            "startTime": 72.0968,
            "endTime": 72.0968
        },
        {
            "noteType": 0,
            "laneNum": 1,
            "startTime": 72.1774,
            "endTime": 72.1774
        },
        {
            "noteType": 0,
            "laneNum": 3,
            "startTime": 72.2581,
            "endTime": 72.2581
        },
        {
            "noteType": 0,
            "laneNum": 2,
            "startTime": 72.3387,
            "endTime": 72.3387
        },
        {
            "noteType": 0,
            "laneNum": 1,
            "startTime": 72.4194,
            "endTime": 72.4194
        },
        {
            "noteType": 0,
            "laneNum": 3,
            "startTime": 72.5,
            "endTime": 72.5
        },
        {
            "noteType": 0,
            "laneNum": 2,
            "startTime": 72.5807,
            "endTime": 72.5807
        },
        {
            "noteType": 0,
            "laneNum": 0,
            "startTime": 72.6613,
            "endTime": 72.6613
        },
        {
            "noteType": 0,
            "laneNum": 1,
            "startTime": 72.7419,
            "endTime": 72.7419
        },
        {
            "noteType": 0,
            "laneNum": 3,
            "startTime": 72.8226,
            "endTime": 72.8226
        },
        {
            "noteType": 0,
            "laneNum": 2,
            "startTime": 72.9032,
            "endTime": 72.9032
        },
        {
            "noteType": 0,
            "laneNum": 1,
            "startTime": 72.9839,
            "endTime": 72.9839
        },
        {
            "noteType": 0,
            "laneNum": 3,
            "startTime": 73.0645,
            "endTime": 73.0645
        },
        {
            "noteType": 0,
            "laneNum": 2,
            "startTime": 73.1452,
            "endTime": 73.1452
        },
        {
            "noteType": 0,
            "laneNum": 3,
            "startTime": 73.2258,
            "endTime": 73.2258
        },
        {
            "noteType": 0,
            "laneNum": 0,
            "startTime": 73.3065,
            "endTime": 73.3065
        },
        {
            "noteType": 0,
            "laneNum": 1,
            "startTime": 73.3871,
            "endTime": 73.3871
        },
        {
            "noteType": 0,
            "laneNum": 2,
            "startTime": 73.4677,
            "endTime": 73.4677
        },
        {
            "noteType": 0,
            "laneNum": 0,
            "startTime": 73.5484,
            "endTime": 73.5484
        },
        {
            "noteType": 0,
            "laneNum": 2,
            "startTime": 73.629,
            "endTime": 73.629
        },
        {
            "noteType": 0,
            "laneNum": 1,
            "startTime": 73.7097,
            "endTime": 73.7097
        },
        {
            "noteType": 0,
            "laneNum": 3,
            "startTime": 73.7903,
            "endTime": 73.7903
        },
        {
            "noteType": 0,
            "laneNum": 0,
            "startTime": 73.871,
            "endTime": 73.871
        },
        {
            "noteType": 0,
            "laneNum": 1,
            "startTime": 73.9516,
            "endTime": 73.9516
        },
        {
            "noteType": 0,
            "laneNum": 3,
            "startTime": 74.0323,
            "endTime": 74.0323
        },
        {
            "noteType": 0,
            "laneNum": 1,
            "startTime": 74.1129,
            "endTime": 74.1129
        },
        {
            "noteType": 0,
            "laneNum": 2,
            "startTime": 74.1936,
            "endTime": 74.1936
        },
        {
            "noteType": 0,
            "laneNum": 0,
            "startTime": 74.2742,
            "endTime": 74.2742
        },
        {
            "noteType": 0,
            "laneNum": 1,
            "startTime": 74.3548,
            "endTime": 74.3548
        },
        {
            "noteType": 0,
            "laneNum": 3,
            "startTime": 74.4355,
            "endTime": 74.4355
        },
        {
            "noteType": 0,
            "laneNum": 2,
            "startTime": 74.5161,
            "endTime": 74.5161
        },
        {
            "noteType": 0,
            "laneNum": 0,
            "startTime": 74.5968,
            "endTime": 74.5968
        },
        {
            "noteType": 0,
            "laneNum": 1,
            "startTime": 74.6774,
            "endTime": 74.6774
        },
        {
            "noteType": 0,
            "laneNum": 0,
            "startTime": 74.7581,
            "endTime": 74.7581
        },
        {
            "noteType": 0,
            "laneNum": 3,
            "startTime": 74.8387,
            "endTime": 74.8387
        },
        {
            "noteType": 0,
            "laneNum": 1,
            "startTime": 74.9194,
            "endTime": 74.9194
        },
        {
            "noteType": 0,
            "laneNum": 2,
            "startTime": 75.0,
            "endTime": 75.0
        },
        {
            "noteType": 0,
            "laneNum": 1,
            "startTime": 75.0806,
            "endTime": 75.0806
        },
        {
            "noteType": 0,
            "laneNum": 3,
            "startTime": 75.1613,
            "endTime": 75.1613
        },
        {
            "noteType": 0,
            "laneNum": 0,
            "startTime": 75.2419,
            "endTime": 75.2419
        },
        {
            "noteType": 0,
            "laneNum": 2,
            "startTime": 75.3226,
            "endTime": 75.3226
        },
        {
            "noteType": 0,
            "laneNum": 3,
            "startTime": 75.4032,
            "endTime": 75.4032
        },
        {
            "noteType": 0,
            "laneNum": 1,
            "startTime": 75.4839,
            "endTime": 75.4839
        },
        {
            "noteType": 0,
            "laneNum": 2,
            "startTime": 75.5645,
            "endTime": 75.5645
        },
        {
            "noteType": 0,
            "laneNum": 3,
            "startTime": 75.6452,
            "endTime": 75.6452
        },
        {
            "noteType": 0,
            "laneNum": 0,
            "startTime": 75.7258,
            "endTime": 75.7258
        },
        {
            "noteType": 0,
            "laneNum": 1,
            "startTime": 75.8065,
            "endTime": 75.8065
        },
        {
            "noteType": 0,
            "laneNum": 3,
            "startTime": 75.8871,
            "endTime": 75.8871
        },
        {
            "noteType": 0,
            "laneNum": 2,
            "startTime": 75.9677,
            "endTime": 75.9677
        },
        {
            "noteType": 0,
            "laneNum": 3,
            "startTime": 76.0484,
            "endTime": 76.0484
        },
        {
            "noteType": 0,
            "laneNum": 1,
            "startTime": 76.129,
            "endTime": 76.129
        },
        {
            "noteType": 0,
            "laneNum": 3,
            "startTime": 76.2097,
            "endTime": 76.2097
        },
        {
            "noteType": 0,
            "laneNum": 2,
            "startTime": 76.2903,
            "endTime": 76.2903
        },
        {
            "noteType": 0,
            "laneNum": 0,
            "startTime": 76.371,
            "endTime": 76.371
        },
        {
            "noteType": 0,
            "laneNum": 1,
            "startTime": 76.4516,
            "endTime": 76.4516
        },
        {
            "noteType": 0,
            "laneNum": 3,
            "startTime": 76.5323,
            "endTime": 76.5323
        },
        {
            "noteType": 0,
            "laneNum": 2,
            "startTime": 76.6129,
            "endTime": 76.6129
        },
        {
            "noteType": 0,
            "laneNum": 1,
            "startTime": 76.6936,
            "endTime": 76.6936
        },
        {
            "noteType": 0,
            "laneNum": 0,
            "startTime": 76.7742,
            "endTime": 76.7742
        },
        {
            "noteType": 0,
            "laneNum": 3,
            "startTime": 76.8548,
            "endTime": 76.8548
        },
        {
            "noteType": 0,
            "laneNum": 2,
            "startTime": 76.9355,
            "endTime": 76.9355
        },
        {
            "noteType": 0,
            "laneNum": 1,
            "startTime": 77.0161,
            "endTime": 77.0161
        },
        {
            "noteType": 0,
            "laneNum": 2,
            "startTime": 77.0968,
            "endTime": 77.0968
        },
        {
            "noteType": 0,
            "laneNum": 0,
            "startTime": 77.1774,
            "endTime": 77.1774
        },
        {
            "noteType": 0,
            "laneNum": 1,
            "startTime": 77.2581,
            "endTime": 77.2581
        },
        {
            "noteType": 0,
            "laneNum": 2,
            "startTime": 77.3387,
            "endTime": 77.3387
        },
        {
            "noteType": 0,
            "laneNum": 3,
            "startTime": 77.4194,
            "endTime": 77.4194
        },
        {
            "noteType": 0,
            "laneNum": 1,
            "startTime": 77.5,
            "endTime": 77.5
        },
        {
            "noteType": 0,
            "laneNum": 2,
            "startTime": 77.5806,
            "endTime": 77.5806
        },
        {
            "noteType": 0,
            "laneNum": 1,
            "startTime": 77.6613,
            "endTime": 77.6613
        },
        {
            "noteType": 0,
            "laneNum": 2,
            "startTime": 77.7419,
            "endTime": 77.7419
        },
        {
            "noteType": 0,
            "laneNum": 0,
            "startTime": 77.8226,
            "endTime": 77.8226
        },
        {
            "noteType": 0,
            "laneNum": 1,
            "startTime": 77.9032,
            "endTime": 77.9032
        },
        {
            "noteType": 0,
            "laneNum": 2,
            "startTime": 77.9839,
            "endTime": 77.9839
        },
        {
            "noteType": 0,
            "laneNum": 0,
            "startTime": 78.0645,
            "endTime": 78.0645
        },
        {
            "noteType": 0,
            "laneNum": 3,
            "startTime": 78.0645,
            "endTime": 78.0645
        },
        {
            "noteType": 0,
            "laneNum": 1,
            "startTime": 78.1452,
            "endTime": 78.1452
        },
        {
            "noteType": 0,
            "laneNum": 2,
            "startTime": 78.2258,
            "endTime": 78.2258
        },
        {
            "noteType": 0,
            "laneNum": 3,
            "startTime": 78.3065,
            "endTime": 78.3065
        },
        {
            "noteType": 0,
            "laneNum": 1,
            "startTime": 78.3871,
            "endTime": 78.3871
        },
        {
            "noteType": 0,
            "laneNum": 2,
            "startTime": 78.4677,
            "endTime": 78.4677
        },
        {
            "noteType": 0,
            "laneNum": 1,
            "startTime": 78.5484,
            "endTime": 78.5484
        },
        {
            "noteType": 0,
            "laneNum": 2,
            "startTime": 78.629,
            "endTime": 78.629
        },
        {
            "noteType": 1,
            "laneNum": 3,
            "startTime": 78.7097,
            "endTime": 80.0
        },
        {
            "noteType": 0,
            "laneNum": 0,
            "startTime": 79.0323,
            "endTime": 79.0323
        },
        {
            "noteType": 0,
            "laneNum": 0,
            "startTime": 79.1935,
            "endTime": 79.1935
        },
        {
            "noteType": 0,
            "laneNum": 0,
            "startTime": 79.3548,
            "endTime": 79.3548
        },
        {
            "noteType": 0,
            "laneNum": 0,
            "startTime": 79.5161,
            "endTime": 79.5161
        },
        {
            "noteType": 0,
            "laneNum": 0,
            "startTime": 79.6774,
            "endTime": 79.6774
        },
        {
            "noteType": 0,
            "laneNum": 0,
            "startTime": 79.8387,
            "endTime": 79.8387
        },
        {
            "noteType": 0,
            "laneNum": 0,
            "startTime": 80.0,
            "endTime": 80.0
        },
        {
            "noteType": 1,
            "laneNum": 2,
            "startTime": 80.0,
            "endTime": 80.6452
        },
        {
            "noteType": 0,
            "laneNum": 0,
            "startTime": 80.6452,
            "endTime": 80.6452
        },
        {
            "noteType": 0,
            "laneNum": 2,
            "startTime": 80.9677,
            "endTime": 80.9677
        },
        {
            "noteType": 1,
            "laneNum": 1,
            "startTime": 81.129,
            "endTime": 82.0968
        },
        {
            "noteType": 0,
            "laneNum": 2,
            "startTime": 82.3387,
            "endTime": 82.3387
        },
        {
            "noteType": 0,
            "laneNum": 3,
            "startTime": 82.5,
            "endTime": 82.5
        },
        {
            "noteType": 0,
            "laneNum": 2,
            "startTime": 82.9032,
            "endTime": 82.9032
        },
        {
            "noteType": 0,
            "laneNum": 1,
            "startTime": 83.2258,
            "endTime": 83.2258
        },
        {
            "noteType": 0,
            "laneNum": 2,
            "startTime": 83.629,
            "endTime": 83.629
        },
        {
            "noteType": 0,
            "laneNum": 3,
            "startTime": 83.7903,
            "endTime": 83.7903
        },
        {
            "noteType": 0,
            "laneNum": 2,
            "startTime": 84.1936,
            "endTime": 84.1936
        },
        {
            "noteType": 0,
            "laneNum": 1,
            "startTime": 84.5161,
            "endTime": 84.5161
        },
        {
            "noteType": 0,
            "laneNum": 0,
            "startTime": 84.9194,
            "endTime": 84.9194
        },
        {
            "noteType": 1,
            "laneNum": 1,
            "startTime": 85.0806,
            "endTime": 85.5645
        },
        {
            "noteType": 0,
            "laneNum": 3,
            "startTime": 85.8065,
            "endTime": 85.8065
        },
        {
            "noteType": 0,
            "laneNum": 2,
            "startTime": 86.129,
            "endTime": 86.129
        },
        {
            "noteType": 1,
            "laneNum": 2,
            "startTime": 86.2903,
            "endTime": 86.7742
        },
        {
            "noteType": 0,
            "laneNum": 0,
            "startTime": 87.0968,
            "endTime": 87.0968
        },
        {
            "noteType": 0,
            "laneNum": 2,
            "startTime": 87.4194,
            "endTime": 87.4194
        },
        {
            "noteType": 1,
            "laneNum": 1,
            "startTime": 87.5807,
            "endTime": 88.0645
        },
        {
            "noteType": 0,
            "laneNum": 1,
            "startTime": 88.3871,
            "endTime": 88.3871
        },
        {
            "noteType": 0,
            "laneNum": 3,
            "startTime": 88.7097,
            "endTime": 88.7097
        },
        {
            "noteType": 1,
            "laneNum": 2,
            "startTime": 88.871,
            "endTime": 89.3548
        },
        {
            "noteType": 1,
            "laneNum": 3,
            "startTime": 89.3548,
            "endTime": 90.0
        },
        {
            "noteType": 0,
            "laneNum": 0,
            "startTime": 90.3226,
            "endTime": 90.3226
        },
        {
            "noteType": 0,
            "laneNum": 2,
            "startTime": 90.9677,
            "endTime": 90.9677
        },
        {
            "noteType": 0,
            "laneNum": 3,
            "startTime": 91.371,
            "endTime": 91.371
        },
        {
            "noteType": 1,
            "laneNum": 2,
            "startTime": 91.5323,
            "endTime": 92.1774
        },
        {
            "noteType": 0,
            "laneNum": 1,
            "startTime": 92.6613,
            "endTime": 92.6613
        },
        {
            "noteType": 0,
            "laneNum": 3,
            "startTime": 92.8226,
            "endTime": 92.8226
        },
        {
            "noteType": 0,
            "laneNum": 2,
            "startTime": 93.2258,
            "endTime": 93.2258
        },
        {
            "noteType": 0,
            "laneNum": 1,
            "startTime": 93.5484,
            "endTime": 93.5484
        },
        {
            "noteType": 0,
            "laneNum": 0,
            "startTime": 93.9516,
            "endTime": 93.9516
        },
        {
            "noteType": 0,
            "laneNum": 2,
            "startTime": 94.1129,
            "endTime": 94.1129
        },
        {
            "noteType": 0,
            "laneNum": 3,
            "startTime": 94.5161,
            "endTime": 94.5161
        },
        {
            "noteType": 0,
            "laneNum": 2,
            "startTime": 94.8387,
            "endTime": 94.8387
        },
        {
            "noteType": 0,
            "laneNum": 1,
            "startTime": 95.1613,
            "endTime": 95.1613
        },
        {
            "noteType": 1,
            "laneNum": 2,
            "startTime": 95.3226,
            "endTime": 95.9677
        },
        {
            "noteType": 0,
            "laneNum": 3,
            "startTime": 96.129,
            "endTime": 96.129
        },
        {
            "noteType": 0,
            "laneNum": 1,
            "startTime": 96.4516,
            "endTime": 96.4516
        },
        {
            "noteType": 1,
            "laneNum": 0,
            "startTime": 96.6129,
            "endTime": 97.2581
        },
        {
            "noteType": 0,
            "laneNum": 3,
            "startTime": 97.4194,
            "endTime": 97.4194
        },
        {
            "noteType": 0,
            "laneNum": 1,
            "startTime": 97.7419,
            "endTime": 97.7419
        },
        {
            "noteType": 1,
            "laneNum": 0,
            "startTime": 97.9032,
            "endTime": 98.5484
        },
        {
            "noteType": 0,
            "laneNum": 1,
            "startTime": 98.7097,
            "endTime": 98.7097
        },
        {
            "noteType": 0,
            "laneNum": 3,
            "startTime": 99.1129,
            "endTime": 99.1129
        },
        {
            "noteType": 0,
            "laneNum": 2,
            "startTime": 99.2742,
            "endTime": 99.2742
        },
        {
            "noteType": 1,
            "laneNum": 1,
            "startTime": 99.6774,
            "endTime": 100.3226
        },
        {
            "noteType": 0,
            "laneNum": 3,
            "startTime": 99.6774,
            "endTime": 99.6774
        },
        {
            "noteType": 0,
            "laneNum": 3,
            "startTime": 99.8387,
            "endTime": 99.8387
        },
        {
            "noteType": 0,
            "laneNum": 2,
            "startTime": 100.0,
            "endTime": 100.0
        },
        {
            "noteType": 0,
            "laneNum": 2,
            "startTime": 100.1613,
            "endTime": 100.1613
        },
        {
            "noteType": 0,
            "laneNum": 0,
            "startTime": 100.3226,
            "endTime": 100.3226
        },
        {
            "noteType": 0,
            "laneNum": 0,
            "startTime": 100.4839,
            "endTime": 100.4839
        },
        {
            "noteType": 0,
            "laneNum": 3,
            "startTime": 100.6452,
            "endTime": 100.6452
        },
        {
            "noteType": 0,
            "laneNum": 1,
            "startTime": 100.9677,
            "endTime": 100.9677
        },
        {
            "noteType": 0,
            "laneNum": 3,
            "startTime": 101.129,
            "endTime": 101.129
        },
        {
            "noteType": 0,
            "laneNum": 3,
            "startTime": 101.2903,
            "endTime": 101.2903
        },
        {
            "noteType": 0,
            "laneNum": 3,
            "startTime": 101.4516,
            "endTime": 101.4516
        },
        {
            "noteType": 0,
            "laneNum": 1,
            "startTime": 101.6129,
            "endTime": 101.6129
        },
        {
            "noteType": 0,
            "laneNum": 3,
            "startTime": 101.9355,
            "endTime": 101.9355
        },
        {
            "noteType": 0,
            "laneNum": 3,
            "startTime": 102.0968,
            "endTime": 102.0968
        },
        {
            "noteType": 0,
            "laneNum": 1,
            "startTime": 102.2581,
            "endTime": 102.2581
        },
        {
            "noteType": 0,
            "laneNum": 3,
            "startTime": 102.5807,
            "endTime": 102.5807
        },
        {
            "noteType": 0,
            "laneNum": 3,
            "startTime": 102.7419,
            "endTime": 102.7419
        },
        {
            "noteType": 0,
            "laneNum": 1,
            "startTime": 102.9032,
            "endTime": 102.9032
        },
        {
            "noteType": 0,
            "laneNum": 0,
            "startTime": 103.2258,
            "endTime": 103.2258
        },
        {
            "noteType": 0,
            "laneNum": 0,
            "startTime": 103.3871,
            "endTime": 103.3871
        },
        {
            "noteType": 0,
            "laneNum": 2,
            "startTime": 103.5484,
            "endTime": 103.5484
        },
        {
            "noteType": 0,
            "laneNum": 0,
            "startTime": 103.871,
            "endTime": 103.871
        },
        {
            "noteType": 0,
            "laneNum": 0,
            "startTime": 104.0323,
            "endTime": 104.0323
        },
        {
            "noteType": 0,
            "laneNum": 2,
            "startTime": 104.1936,
            "endTime": 104.1936
        },
        {
            "noteType": 0,
            "laneNum": 1,
            "startTime": 104.5161,
            "endTime": 104.5161
        },
        {
            "noteType": 0,
            "laneNum": 1,
            "startTime": 104.6774,
            "endTime": 104.6774
        },
        {
            "noteType": 0,
            "laneNum": 1,
            "startTime": 104.8387,
            "endTime": 104.8387
        },
        {
            "noteType": 0,
            "laneNum": 3,
            "startTime": 105.0,
            "endTime": 105.0
        },
        {
            "noteType": 0,
            "laneNum": 2,
            "startTime": 105.3226,
            "endTime": 105.3226
        },
        {
            "noteType": 0,
            "laneNum": 1,
            "startTime": 105.6452,
            "endTime": 105.6452
        },
        {
            "noteType": 0,
            "laneNum": 0,
            "startTime": 106.129,
            "endTime": 106.129
        },
        {
            "noteType": 0,
            "laneNum": 0,
            "startTime": 106.4516,
            "endTime": 106.4516
        },
        {
            "noteType": 0,
            "laneNum": 0,
            "startTime": 106.7742,
            "endTime": 106.7742
        },
        {
            "noteType": 1,
            "laneNum": 2,
            "startTime": 107.0968,
            "endTime": 108.3871
        },
        {
            "noteType": 0,
            "laneNum": 3,
            "startTime": 108.3871,
            "endTime": 108.3871
        },
        {
            "noteType": 0,
            "laneNum": 1,
            "startTime": 108.7097,
            "endTime": 108.7097
        },
        {
            "noteType": 0,
            "laneNum": 2,
            "startTime": 108.871,
            "endTime": 108.871
        },
        {
            "noteType": 0,
            "laneNum": 3,
            "startTime": 109.3548,
            "endTime": 109.3548
        },
        {
            "noteType": 0,
            "laneNum": 2,
            "startTime": 110.0,
            "endTime": 110.0
        },
        {
            "noteType": 0,
            "laneNum": 2,
            "startTime": 110.3226,
            "endTime": 110.3226
        },
        {
            "noteType": 0,
            "laneNum": 1,
            "startTime": 110.4032,
            "endTime": 110.4032
        },
        {
            "noteType": 0,
            "laneNum": 0,
            "startTime": 110.4839,
            "endTime": 110.4839
        },
        {
            "noteType": 0,
            "laneNum": 2,
            "startTime": 110.6452,
            "endTime": 110.6452
        },
        {
            "noteType": 0,
            "laneNum": 3,
            "startTime": 110.8065,
            "endTime": 110.8065
        },
        {
            "noteType": 1,
            "laneNum": 2,
            "startTime": 110.9677,
            "endTime": 111.6129
        },
        {
            "noteType": 1,
            "laneNum": 0,
            "startTime": 111.6129,
            "endTime": 112.2581
        },
        {
            "noteType": 1,
            "laneNum": 1,
            "startTime": 112.2581,
            "endTime": 112.9032
        },
        {
            "noteType": 1,
            "laneNum": 3,
            "startTime": 112.9032,
            "endTime": 113.3871
        },
        {
            "noteType": 1,
            "laneNum": 0,
            "startTime": 113.3871,
            "endTime": 114.3548
        },
        {
            "noteType": 1,
            "laneNum": 1,
            "startTime": 114.3548,
            "endTime": 115.0
        },
        {
            "noteType": 1,
            "laneNum": 2,
            "startTime": 115.0,
            "endTime": 118.0645
        },
        {
            "noteType": 0,
            "laneNum": 1,
            "startTime": 118.0645,
            "endTime": 118.0645
        },
        {
            "noteType": 0,
            "laneNum": 1,
            "startTime": 118.2258,
            "endTime": 118.2258
        },
        {
            "noteType": 0,
            "laneNum": 1,
            "startTime": 118.3871,
            "endTime": 118.3871
        },
        {
            "noteType": 0,
            "laneNum": 3,
            "startTime": 118.5484,
            "endTime": 118.5484
        },
        {
            "noteType": 0,
            "laneNum": 2,
            "startTime": 118.871,
            "endTime": 118.871
        },
        {
            "noteType": 0,
            "laneNum": 0,
            "startTime": 119.0323,
            "endTime": 119.0323
        },
        {
            "noteType": 0,
            "laneNum": 1,
            "startTime": 119.1936,
            "endTime": 119.1936
        },
        {
            "noteType": 0,
            "laneNum": 2,
            "startTime": 119.5161,
            "endTime": 119.5161
        },
        {
            "noteType": 0,
            "laneNum": 2,
            "startTime": 119.6774,
            "endTime": 119.6774
        },
        {
            "noteType": 0,
            "laneNum": 2,
            "startTime": 120.0,
            "endTime": 120.0
        }
    ]
}